{"_id":{"$oid":"5c98d4eae2939d0fe0b96670"},"ProductionBudget":"N/A","Movie":"Apollo 11","ReleaseDate":{"$date":"2019-03-01T00:00:00.000Z"},"Genre":"Documentary","Distributor":"Neon","Runtime":"1 hrs. 33 min.","MPAARating":"G"}
{"_id":{"$oid":"5c98d4ece2939d0fe0b96671"},"ProductionBudget":"N/A","Movie":"Avant qu'on explose","ReleaseDate":{"$date":"2019-03-01T00:00:00.000Z"},"Genre":"Comedy","Distributor":"Entertainment One","Runtime":"1 hrs. 48 min.","MPAARating":"Unrated"}
{"_id":{"$oid":"5c98d4f1e2939d0fe0b96672"},"ProductionBudget":"N/A","Movie":"Chokehold","ReleaseDate":{"$date":"2019-03-01T00:00:00.000Z"},"Genre":"Action Drama","Distributor":"Ammo Content","Runtime":"1 hrs. 38 min.","MPAARating":"Unrated"}
{"_id":{"$oid":"5c98d4f2e2939d0fe0b96673"},"ProductionBudget":"N/A","Movie":"Cliffs of Freedom","ReleaseDate":{"$date":"2019-03-01T00:00:00.000Z"},"Genre":"Historical Drama","Distributor":"Round Hill Media","Runtime":"2 hrs. 17 min.","MPAARating":"R"}
{"_id":{"$oid":"5c98d4f3e2939d0fe0b96674"},"ProductionBudget":"N/A","Movie":"Climax","ReleaseDate":{"$date":"2019-03-01T00:00:00.000Z"},"Genre":"Horror","Distributor":"A24","Runtime":"1 hrs. 36 min.","MPAARating":"R"}
{"_id":{"$oid":"5c98d4f8e2939d0fe0b96675"},"ProductionBudget":"N/A","Movie":"Furie","ReleaseDate":{"$date":"2019-03-01T00:00:00.000Z"},"Genre":"Action / Adventure","Distributor":"Well Go USA","Runtime":"1 hrs. 38 min.","MPAARating":"Unrated"}
{"_id":{"$oid":"5c98d4fae2939d0fe0b96676"},"ProductionBudget":"N/A","Movie":"Giant Little Ones","ReleaseDate":{"$date":"2019-03-01T00:00:00.000Z"},"Genre":"Drama","Distributor":"Vertical Entertainment","Runtime":"1 hrs. 34 min.","MPAARating":"R"}
{"_id":{"$oid":"5c98d4fce2939d0fe0b96677"},"ProductionBudget":"N/A","Movie":"Greta","ReleaseDate":{"$date":"2019-03-01T00:00:00.000Z"},"Genre":"Drama / Thriller","Distributor":"Focus Features","Runtime":"1 hrs. 38 min.","MPAARating":"R"}
{"_id":{"$oid":"5c98d4fee2939d0fe0b96678"},"ProductionBudget":"N/A","Movie":"He Matado a mi Marido!","ReleaseDate":{"$date":"2019-03-01T00:00:00.000Z"},"Genre":"Comedy","Distributor":"Hammond","Runtime":"1 hrs. 43 min.","MPAARating":"Unrated"}
{"_id":{"$oid":"5c98d500e2939d0fe0b96679"},"ProductionBudget":"N/A","Movie":"The Hole in the Ground","ReleaseDate":{"$date":"2019-03-01T00:00:00.000Z"},"Genre":"Horror","Distributor":"A24","Runtime":"1 hrs. 30 min.","MPAARating":"R"}
{"_id":{"$oid":"5c98d501e2939d0fe0b9667a"},"ProductionBudget":"N/A","Movie":"The Hours and Times (2019 re-release)","ReleaseDate":{"$date":"2019-03-01T00:00:00.000Z"},"Genre":"Drama","Distributor":"Oscilloscope Pictures","Runtime":"0 hrs. 58 min.","MPAARating":"Unrated"}
{"_id":{"$oid":"5c98d503e2939d0fe0b9667b"},"ProductionBudget":"N/A","Movie":"Joseph Pulitzer: Voice of the People","ReleaseDate":{"$date":"2019-03-01T00:00:00.000Z"},"Genre":"Documentary","Distributor":"First Run","Runtime":"1 hrs. 24 min.","MPAARating":"Unrated"}
{"_id":{"$oid":"5c98d505e2939d0fe0b9667c"},"ProductionBudget":"N/A","Movie":"Luka Chuppi","ReleaseDate":{"$date":"2019-03-01T00:00:00.000Z"},"Genre":"Comedy","Distributor":"Viva Pictures Distribution","Runtime":"2 hrs. 6 min.","MPAARating":"Unrated"}
{"_id":{"$oid":"5c98d507e2939d0fe0b9667d"},"ProductionBudget":"N/A","Movie":"Mapplethorpe","ReleaseDate":{"$date":"2019-03-01T00:00:00.000Z"},"Genre":"Drama","Distributor":"Samuel Goldwyn","Runtime":"1 hrs. 42 min.","MPAARating":"Unrated"}
{"_id":{"$oid":"5c98d508e2939d0fe0b9667e"},"ProductionBudget":"N/A","Movie":"Saint Judy","ReleaseDate":{"$date":"2019-03-01T00:00:00.000Z"},"Genre":"Drama","Distributor":"Blue Fox Entertainment","Runtime":"1 hrs. 46 min.","MPAARating":"PG-13"}
{"_id":{"$oid":"5c98d509e2939d0fe0b9667f"},"ProductionBudget":"N/A","Movie":"Sonchiriya","ReleaseDate":{"$date":"2019-03-01T00:00:00.000Z"},"Genre":"Action / Crime","Distributor":"PackYourBag","Runtime":"2 hrs. 23 min.","MPAARating":"Unrated"}
{"_id":{"$oid":"5c98d50be2939d0fe0b96680"},"ProductionBudget":"N/A","Movie":"The Sower","ReleaseDate":{"$date":"2019-03-01T00:00:00.000Z"},"Genre":"Drama","Distributor":"Film Movement","Runtime":"1 hrs. 38 min.","MPAARating":"Unrated"}
{"_id":{"$oid":"5c98d50ee2939d0fe0b96681"},"ProductionBudget":"N/A","Movie":"This Magnificent Cake!","ReleaseDate":{"$date":"2019-03-01T00:00:00.000Z"},"Genre":"Animation","Distributor":"GKIDS","Runtime":"0 hrs. 44 min.","MPAARating":"Unrated"}
{"_id":{"$oid":"5c98d510e2939d0fe0b96682"},"ProductionBudget":"N/A","Movie":"Transit","ReleaseDate":{"$date":"2019-03-01T00:00:00.000Z"},"Genre":"Drama","Distributor":"Music Box Films","Runtime":"1 hrs. 41 min.","MPAARating":"Unrated"}
{"_id":{"$oid":"5c98d511e2939d0fe0b96683"},"ProductionBudget":"N/A","Movie":"Tyler Perry's A Madea Family Funeral","ReleaseDate":{"$date":"2019-03-01T00:00:00.000Z"},"Genre":"Comedy","Distributor":"Lionsgate","Runtime":"1 hrs. 49 min.","MPAARating":"PG-13"}
{"_id":{"$oid":"5c98d513e2939d0fe0b96684"},"ProductionBudget":"N/A","Movie":"Virginia Minnesota","ReleaseDate":{"$date":"2019-03-01T00:00:00.000Z"},"Genre":"Comedy / Drama","Distributor":"Indican","Runtime":"1 hrs. 38 min.","MPAARating":"Unrated"}
{"_id":{"$oid":"5c98d514e2939d0fe0b96685"},"ProductionBudget":"N/A","Movie":"The Wedding Guest","ReleaseDate":{"$date":"2019-03-01T00:00:00.000Z"},"Genre":"Thriller","Distributor":"IFC","Runtime":"1 hrs. 34 min.","MPAARating":"R"}
{"_id":{"$oid":"5c98d516e2939d0fe0b96686"},"ProductionBudget":"N/A","Movie":"Woman at War","ReleaseDate":{"$date":"2019-03-01T00:00:00.000Z"},"Genre":"Action Drama","Distributor":"Magnolia","Runtime":"1 hrs. 41 min.","MPAARating":"Unrated"}
{"_id":{"$oid":"5c98d517e2939d0fe0b96687"},"ProductionBudget":"N/A","Movie":"3 Faces","ReleaseDate":{"$date":"2019-03-08T00:00:00.000Z"},"Genre":"Drama","Distributor":"Kino Lorber","Runtime":"1 hrs. 40 min.","MPAARating":"Unrated"}
{"_id":{"$oid":"5c98d519e2939d0fe0b96688"},"ProductionBudget":"N/A","Movie":"Babylon (2019 re-release)","ReleaseDate":{"$date":"2019-03-08T00:00:00.000Z"},"Genre":"Drama","Distributor":"Kino Lorber","Runtime":"1 hrs. 35 min.","MPAARating":"Unrated"}
{"_id":{"$oid":"5c98d51ce2939d0fe0b96689"},"ProductionBudget":"N/A","Movie":"Badla","ReleaseDate":{"$date":"2019-03-08T00:00:00.000Z"},"Genre":"Crime","Distributor":"Reliance Big Pictures","Runtime":"1 hrs. 58 min.","MPAARating":"Unrated"}
{"_id":{"$oid":"5c98d51ee2939d0fe0b9668a"},"ProductionBudget":"N/A","Movie":"Captain Marvel","ReleaseDate":{"$date":"2019-03-08T00:00:00.000Z"},"Genre":"Action / Adventure","Distributor":"Buena Vista","Runtime":"2 hrs. 8 min.","MPAARating":"PG-13"}
{"_id":{"$oid":"5c98d520e2939d0fe0b9668b"},"ProductionBudget":"N/A","Movie":"An Elephant Sitting Still","ReleaseDate":{"$date":"2019-03-08T00:00:00.000Z"},"Genre":"Drama","Distributor":"KimStim","Runtime":"3 hrs. 54 min.","MPAARating":"Unrated"}
{"_id":{"$oid":"5c98d521e2939d0fe0b9668c"},"ProductionBudget":"N/A","Movie":"Ferrante Fever","ReleaseDate":{"$date":"2019-03-08T00:00:00.000Z"},"Genre":"Documentary","Distributor":"Greenwich","Runtime":"1 hrs. 14 min.","MPAARating":"Unrated"}
{"_id":{"$oid":"5c98d522e2939d0fe0b9668d"},"ProductionBudget":"N/A","Movie":"Gloria Bell","ReleaseDate":{"$date":"2019-03-08T00:00:00.000Z"},"Genre":"Drama","Distributor":"A24","Runtime":"1 hrs. 42 min.","MPAARating":"R"}
{"_id":{"$oid":"5c98d524e2939d0fe0b9668e"},"ProductionBudget":"N/A","Movie":"The Kid (2019)","ReleaseDate":{"$date":"2019-03-08T00:00:00.000Z"},"Genre":"Action Drama","Distributor":"Lionsgate","Runtime":"1 hrs. 40 min.","MPAARating":"R"}
{"_id":{"$oid":"5c98d526e2939d0fe0b9668f"},"ProductionBudget":"N/A","Movie":"The Sex Trip","ReleaseDate":{"$date":"2019-03-08T00:00:00.000Z"},"Genre":"Comedy","Distributor":"Ammo Content","Runtime":"1 hrs. 30 min.","MPAARating":"Unrated"}
{"_id":{"$oid":"5c98d528e2939d0fe0b96690"},"ProductionBudget":"N/A","Movie":"Black Mother","ReleaseDate":{"$date":"2019-03-09T00:00:00.000Z"},"Genre":"Documentary","Distributor":"Grasshopper Film","Runtime":"1 hrs. 17 min.","MPAARating":"Unrated"}
{"_id":{"$oid":"5c98d529e2939d0fe0b96691"},"ProductionBudget":"N/A","Movie":"Bolshoi Ballet: Sleeping Beauty (2019)","ReleaseDate":{"$date":"2019-03-10T00:00:00.000Z"},"Genre":"Unknown","Distributor":"Fathom","Runtime":"N/A","MPAARating":"Unknown"}
{"_id":{"$oid":"5c98d52ce2939d0fe0b96692"},"ProductionBudget":"N/A","Movie":"311 Enlarged to Show Detail 3","ReleaseDate":{"$date":"2019-03-11T00:00:00.000Z"},"Genre":"Concert","Distributor":"Trafalgar Releasing","Runtime":"2 hrs. 13 min.","MPAARating":"Unrated"}
{"_id":{"$oid":"5c98d52ee2939d0fe0b96693"},"ProductionBudget":"N/A","Movie":"Doctor Who: Logopolis","ReleaseDate":{"$date":"2019-03-13T00:00:00.000Z"},"Genre":"Sci-Fi","Distributor":"Fathom","Runtime":"N/A","MPAARating":"Unrated"}
{"_id":{"$oid":"5c98d52fe2939d0fe0b96694"},"ProductionBudget":"N/A","Movie":"Dominirriquenos 2","ReleaseDate":{"$date":"2019-03-14T00:00:00.000Z"},"Genre":"Sports Comedy","Distributor":"Spanglish Movies","Runtime":"N/A","MPAARating":"Unrated"}
{"_id":{"$oid":"5c98d530e2939d0fe0b96695"},"ProductionBudget":"N/A","Movie":"Fate/Stay Night: Heaven's Feel - II. Lost Butterfly","ReleaseDate":{"$date":"2019-03-14T00:00:00.000Z"},"Genre":"Animation","Distributor":"Fathom","Runtime":"1 hrs. 57 min.","MPAARating":"Unknown"}
{"_id":{"$oid":"5c98d532e2939d0fe0b96696"},"ProductionBudget":"N/A","Movie":"Patterns of Evidence: The Moses Controversy","ReleaseDate":{"$date":"2019-03-14T00:00:00.000Z"},"Genre":"Unknown","Distributor":"Fathom","Runtime":"N/A","MPAARating":"Unrated"}
{"_id":{"$oid":"5c98d535e2939d0fe0b96697"},"ProductionBudget":"N/A","Movie":"The Aftermath","ReleaseDate":{"$date":"2019-03-15T00:00:00.000Z"},"Genre":"War Drama","Distributor":"Fox Searchlight","Runtime":"1 hrs. 48 min.","MPAARating":"R"}
{"_id":{"$oid":"5c98d538e2939d0fe0b96698"},"ProductionBudget":"N/A","Movie":"Ash is Purest White","ReleaseDate":{"$date":"2019-03-15T00:00:00.000Z"},"Genre":"Drama","Distributor":"Cohen Media Group","Runtime":"2 hrs. 17 min.","MPAARating":"Unrated"}
{"_id":{"$oid":"5c98d539e2939d0fe0b96699"},"ProductionBudget":"N/A","Movie":"Captive State","ReleaseDate":{"$date":"2019-03-15T00:00:00.000Z"},"Genre":"Sci-Fi","Distributor":"Focus Features","Runtime":"1 hrs. 49 min.","MPAARating":"Not Yet Rated"}
{"_id":{"$oid":"5c98d53be2939d0fe0b9669a"},"ProductionBudget":"N/A","Movie":"Chimera Strain","ReleaseDate":{"$date":"2019-03-15T00:00:00.000Z"},"Genre":"Sci-Fi","Distributor":"Vertical Entertainment","Runtime":"1 hrs. 20 min.","MPAARating":"R"}
{"_id":{"$oid":"5c98d53de2939d0fe0b9669b"},"ProductionBudget":"N/A","Movie":"Combat Obscura","ReleaseDate":{"$date":"2019-03-15T00:00:00.000Z"},"Genre":"Documentary","Distributor":"Oscilloscope Pictures","Runtime":"1 hrs. 10 min.","MPAARating":"Unrated"}
{"_id":{"$oid":"5c98d53fe2939d0fe0b9669c"},"ProductionBudget":"N/A","Movie":"The Crossing","ReleaseDate":{"$date":"2019-03-15T00:00:00.000Z"},"Genre":"Drama","Distributor":"CMC","Runtime":"1 hrs. 39 min.","MPAARating":"Unrated"}
{"_id":{"$oid":"5c98d542e2939d0fe0b9669d"},"ProductionBudget":"N/A","Movie":"The Eyes of Orson Welles","ReleaseDate":{"$date":"2019-03-15T00:00:00.000Z"},"Genre":"Documentary","Distributor":"Janus Films","Runtime":"1 hrs. 55 min.","MPAARating":"Unrated"}
{"_id":{"$oid":"5c98d543e2939d0fe0b9669e"},"ProductionBudget":"N/A","Movie":"Faith, Hope \u0026 Love","ReleaseDate":{"$date":"2019-03-15T00:00:00.000Z"},"Genre":"Romantic Comedy","Distributor":"ArtAffects","Runtime":"1 hrs. 46 min.","MPAARating":"PG"}
{"_id":{"$oid":"5c98d544e2939d0fe0b9669f"},"ProductionBudget":"N/A","Movie":"Five Feet Apart","ReleaseDate":{"$date":"2019-03-15T00:00:00.000Z"},"Genre":"Romance","Distributor":"Lionsgate","Runtime":"1 hrs. 56 min.","MPAARating":"PG-13"}
{"_id":{"$oid":"5c98d546e2939d0fe0b966a0"},"ProductionBudget":"N/A","Movie":"Frantz Fanon: Black Skin, White Mask","ReleaseDate":{"$date":"2019-03-15T00:00:00.000Z"},"Genre":"Documentary","Distributor":"Film Movement","Runtime":"1 hrs. 10 min.","MPAARating":"Unrated"}
{"_id":{"$oid":"5c98d548e2939d0fe0b966a1"},"ProductionBudget":"N/A","Movie":"The Hummingbird Project","ReleaseDate":{"$date":"2019-03-15T00:00:00.000Z"},"Genre":"Comedy / Drama","Distributor":"The Orchard","Runtime":"1 hrs. 51 min.","MPAARating":"R"}
{"_id":{"$oid":"5c98d549e2939d0fe0b966a2"},"ProductionBudget":"N/A","Movie":"Iceman (2019)","ReleaseDate":{"$date":"2019-03-15T00:00:00.000Z"},"Genre":"Thriller","Distributor":"Film Movement","Runtime":"1 hrs. 36 min.","MPAARating":"Unrated"}
{"_id":{"$oid":"5c98d54be2939d0fe0b966a3"},"ProductionBudget":"N/A","Movie":"Knife+Heart","ReleaseDate":{"$date":"2019-03-15T00:00:00.000Z"},"Genre":"Drama","Distributor":"Altered Innocence","Runtime":"1 hrs. 50 min.","MPAARating":"Unrated"}
{"_id":{"$oid":"5c98d54de2939d0fe0b966a4"},"ProductionBudget":"N/A","Movie":"More than Blue","ReleaseDate":{"$date":"2019-03-15T00:00:00.000Z"},"Genre":"Romance","Distributor":"China Lion","Runtime":"1 hrs. 45 min.","MPAARating":"Unrated"}
{"_id":{"$oid":"5c98d54fe2939d0fe0b966a5"},"ProductionBudget":"N/A","Movie":"The Mustang","ReleaseDate":{"$date":"2019-03-15T00:00:00.000Z"},"Genre":"Drama","Distributor":"Focus Features","Runtime":"1 hrs. 36 min.","MPAARating":"R"}
{"_id":{"$oid":"5c98d550e2939d0fe0b966a6"},"ProductionBudget":"N/A","Movie":"Nancy Drew and the Hidden Staircase","ReleaseDate":{"$date":"2019-03-15T00:00:00.000Z"},"Genre":"Family","Distributor":"Warner Bros.","Runtime":"1 hrs. 29 min.","MPAARating":"PG"}
{"_id":{"$oid":"5c98d552e2939d0fe0b966a7"},"ProductionBudget":"N/A","Movie":"No Manches Frida 2","ReleaseDate":{"$date":"2019-03-15T00:00:00.000Z"},"Genre":"Comedy","Distributor":"Pantelion","Runtime":"1 hrs. 42 min.","MPAARating":"R"}
{"_id":{"$oid":"5c98d553e2939d0fe0b966a8"},"ProductionBudget":"N/A","Movie":"Off Season","ReleaseDate":{"$date":"2019-03-15T00:00:00.000Z"},"Genre":"Drama / Thriller","Distributor":"Indican","Runtime":"1 hrs. 26 min.","MPAARating":"Unrated"}
{"_id":{"$oid":"5c98d555e2939d0fe0b966a9"},"ProductionBudget":"N/A","Movie":"Wonder Park","ReleaseDate":{"$date":"2019-03-15T00:00:00.000Z"},"Genre":"Animation","Distributor":"Paramount","Runtime":"1 hrs. 26 min.","MPAARating":"PG"}
{"_id":{"$oid":"5c98d556e2939d0fe0b966aa"},"ProductionBudget":"N/A","Movie":"Yardie","ReleaseDate":{"$date":"2019-03-15T00:00:00.000Z"},"Genre":"Crime Drama","Distributor":"Rialto","Runtime":"1 hrs. 43 min.","MPAARating":"Unrated"}
{"_id":{"$oid":"5c98d55fe2939d0fe0b966ab"},"ProductionBudget":"N/A","Movie":"Triple Threat","ReleaseDate":{"$date":"2019-03-19T00:00:00.000Z"},"Genre":"Action / Adventure","Distributor":"Well Go USA","Runtime":"1 hrs. 36 min.","MPAARating":"R"}
{"_id":{"$oid":"5c98d569e2939d0fe0b966ac"},"ProductionBudget":"N/A","Movie":"Cruel Intentions (20th Anniversary)","ReleaseDate":{"$date":"2019-03-22T00:00:00.000Z"},"Genre":"Romantic Thriller","Distributor":"Sony / Columbia","Runtime":"1 hrs. 37 min.","MPAARating":"R"}
{"_id":{"$oid":"5c98d56be2939d0fe0b966ad"},"ProductionBudget":"N/A","Movie":"Hotel Mumbai","ReleaseDate":{"$date":"2019-03-22T00:00:00.000Z"},"Genre":"Drama","Distributor":"Bleecker Street","Runtime":"2 hrs. 5 min.","MPAARating":"R"}
{"_id":{"$oid":"5c98d56ce2939d0fe0b966ae"},"ProductionBudget":"N/A","Movie":"Out of Blue","ReleaseDate":{"$date":"2019-03-22T00:00:00.000Z"},"Genre":"Crime Drama","Distributor":"IFC","Runtime":"1 hrs. 49 min.","MPAARating":"Unrated"}
{"_id":{"$oid":"5c98d56ee2939d0fe0b966af"},"ProductionBudget":"N/A","Movie":"Ramen Shop","ReleaseDate":{"$date":"2019-03-22T00:00:00.000Z"},"Genre":"Comedy / Drama","Distributor":"Strand","Runtime":"1 hrs. 30 min.","MPAARating":"Unrated"}
{"_id":{"$oid":"5c98d574e2939d0fe0b966b1"},"ProductionBudget":"$20 million","Movie":"Us","ReleaseDate":{"$date":"2019-03-22T00:00:00.000Z"},"Genre":"Thriller","Distributor":"Universal","Runtime":"1 hrs. 56 min.","MPAARating":"R"}
{"_id":{"$oid":"5c98d576e2939d0fe0b966b2"},"ProductionBudget":"N/A","Movie":"The Beach Bum","ReleaseDate":{"$date":"2019-03-29T00:00:00.000Z"},"Genre":"Comedy","Distributor":"Neon","Runtime":"1 hrs. 35 min.","MPAARating":"R"}
{"_id":{"$oid":"5c98d577e2939d0fe0b966b3"},"ProductionBudget":"N/A","Movie":"Diane","ReleaseDate":{"$date":"2019-03-29T00:00:00.000Z"},"Genre":"Drama","Distributor":"IFC","Runtime":"1 hrs. 35 min.","MPAARating":"Unrated"}
{"_id":{"$oid":"5c98d578e2939d0fe0b966b4"},"ProductionBudget":"N/A","Movie":"Dumbo (2019)","ReleaseDate":{"$date":"2019-03-29T00:00:00.000Z"},"Genre":"Adventure","Distributor":"Buena Vista","Runtime":"1 hrs. 55 min.","MPAARating":"PG"}
{"_id":{"$oid":"5c98d57ae2939d0fe0b966b5"},"ProductionBudget":"N/A","Movie":"Notebook","ReleaseDate":{"$date":"2019-03-29T00:00:00.000Z"},"Genre":"Drama","Distributor":"Yash Raj","Runtime":"N/A","MPAARating":"Unrated"}
{"_id":{"$oid":"5c98d57be2939d0fe0b966b6"},"ProductionBudget":"N/A","Movie":"Screwball","ReleaseDate":{"$date":"2019-03-29T00:00:00.000Z"},"Genre":"Documentary","Distributor":"Greenwich","Runtime":"1 hrs. 45 min.","MPAARating":"Unrated"}
{"_id":{"$oid":"5c98d57de2939d0fe0b966b7"},"ProductionBudget":"N/A","Movie":"Trinity Seven: Heavens Library \u0026 Crimson Lord","ReleaseDate":{"$date":"2019-03-29T00:00:00.000Z"},"Genre":"Animation","Distributor":"Atlas Distribution","Runtime":"1 hrs. 1 min.","MPAARating":"R"}
{"_id":{"$oid":"5c98d57fe2939d0fe0b966b8"},"ProductionBudget":"N/A","Movie":"Unplanned","ReleaseDate":{"$date":"2019-03-29T00:00:00.000Z"},"Genre":"Drama","Distributor":"Pure Flix","Runtime":"1 hrs. 50 min.","MPAARating":"R"}
{"_id":{"$oid":"5c98d583e2939d0fe0b966b9"},"ProductionBudget":"N/A","Movie":"Khalid: Free Spirit","ReleaseDate":{"$date":"2019-04-03T00:00:00.000Z"},"Genre":"Concert","Distributor":"Trafalgar Releasing","Runtime":"1 hrs. 35 min.","MPAARating":"Unrated"}
{"_id":{"$oid":"5c98d586e2939d0fe0b966ba"},"ProductionBudget":"N/A","Movie":"Amazing Grace (2019)","ReleaseDate":{"$date":"2019-04-05T00:00:00.000Z"},"Genre":"Documentary","Distributor":"Neon","Runtime":"1 hrs. 27 min.","MPAARating":"G"}
{"_id":{"$oid":"5c98d58ae2939d0fe0b966bb"},"ProductionBudget":"N/A","Movie":"The Best of Enemies","ReleaseDate":{"$date":"2019-04-05T00:00:00.000Z"},"Genre":"Drama","Distributor":"STX Entertainment","Runtime":"N/A","MPAARating":"Not Yet Rated"}
{"_id":{"$oid":"5c98d58ce2939d0fe0b966bc"},"ProductionBudget":"N/A","Movie":"Billboard","ReleaseDate":{"$date":"2019-04-05T00:00:00.000Z"},"Genre":"Drama","Distributor":"iDreamMachine","Runtime":"1 hrs. 29 min.","MPAARating":"Unrated"}
{"_id":{"$oid":"5c98d590e2939d0fe0b966bd"},"ProductionBudget":"N/A","Movie":"Pet Sematary (2019)","ReleaseDate":{"$date":"2019-04-05T00:00:00.000Z"},"Genre":"Horror","Distributor":"Paramount","Runtime":"1 hrs. 41 min.","MPAARating":"R"}
{"_id":{"$oid":"5c98d596e2939d0fe0b966be"},"ProductionBudget":"N/A","Movie":"The Public","ReleaseDate":{"$date":"2019-04-05T00:00:00.000Z"},"Genre":"Drama","Distributor":"Greenwich","Runtime":"2 hrs. 2 min.","MPAARating":"PG-13"}
{"_id":{"$oid":"5c98d597e2939d0fe0b966bf"},"ProductionBudget":"N/A","Movie":"Shazam!","ReleaseDate":{"$date":"2019-04-05T00:00:00.000Z"},"Genre":"Action","Distributor":"Warner Bros. (New Line)","Runtime":"2 hrs. 12 min.","MPAARating":"PG-13"}
{"_id":{"$oid":"5c98d59be2939d0fe0b966c0"},"ProductionBudget":"N/A","Movie":"Suburban Birds","ReleaseDate":{"$date":"2019-04-05T00:00:00.000Z"},"Genre":"Drama","Distributor":"Cinema Guild","Runtime":"1 hrs. 53 min.","MPAARating":"Unknown"}
{"_id":{"$oid":"5c98d59de2939d0fe0b966c1"},"ProductionBudget":"N/A","Movie":"Teen Spirit","ReleaseDate":{"$date":"2019-04-05T00:00:00.000Z"},"Genre":"Drama","Distributor":"Bleecker Street","Runtime":"1 hrs. 32 min.","MPAARating":"PG-13"}
{"_id":{"$oid":"5c98d5a0e2939d0fe0b966c2"},"ProductionBudget":"N/A","Movie":"Sauvage","ReleaseDate":{"$date":"2019-04-10T00:00:00.000Z"},"Genre":"Drama","Distributor":"Strand","Runtime":"1 hrs. 37 min.","MPAARating":"Unrated"}
{"_id":{"$oid":"5c98d5a3e2939d0fe0b966c3"},"ProductionBudget":"N/A","Movie":"After (2019)","ReleaseDate":{"$date":"2019-04-12T00:00:00.000Z"},"Genre":"Drama","Distributor":"Aviron","Runtime":"N/A","MPAARating":"Not Yet Rated"}
{"_id":{"$oid":"5c98d5a5e2939d0fe0b966c4"},"ProductionBudget":"N/A","Movie":"A Dark Place","ReleaseDate":{"$date":"2019-04-12T00:00:00.000Z"},"Genre":"Thriller","Distributor":"Shout! Factory","Runtime":"1 hrs. 29 min.","MPAARating":"Unrated"}
{"_id":{"$oid":"5c98d5abe2939d0fe0b966c5"},"ProductionBudget":"N/A","Movie":"Hellboy (2019)","ReleaseDate":{"$date":"2019-04-12T00:00:00.000Z"},"Genre":"Action","Distributor":"Lionsgate/Summit","Runtime":"N/A","MPAARating":"R"}
{"_id":{"$oid":"5c98d5ace2939d0fe0b966c6"},"ProductionBudget":"N/A","Movie":"Little","ReleaseDate":{"$date":"2019-04-12T00:00:00.000Z"},"Genre":"Comedy","Distributor":"Universal","Runtime":"N/A","MPAARating":"PG-13"}
{"_id":{"$oid":"5c98d5b0e2939d0fe0b966c7"},"ProductionBudget":"N/A","Movie":"Missing Link","ReleaseDate":{"$date":"2019-04-12T00:00:00.000Z"},"Genre":"Animation","Distributor":"United Artists Releasing","Runtime":"1 hrs. 35 min.","MPAARating":"PG"}
{"_id":{"$oid":"5c98d5b2e2939d0fe0b966c8"},"ProductionBudget":"N/A","Movie":"Rottentail","ReleaseDate":{"$date":"2019-04-12T00:00:00.000Z"},"Genre":"Horror","Distributor":"Ammo Content","Runtime":"1 hrs. 29 min.","MPAARating":"Unrated"}
{"_id":{"$oid":"5c98d5b5e2939d0fe0b966c9"},"ProductionBudget":"N/A","Movie":"Wild Nights With Emily","ReleaseDate":{"$date":"2019-04-12T00:00:00.000Z"},"Genre":"Comedy","Distributor":"Greenwich","Runtime":"1 hrs. 25 min.","MPAARating":"PG-13"}
{"_id":{"$oid":"5c98d5b6e2939d0fe0b966ca"},"ProductionBudget":"N/A","Movie":"Breakthrough","ReleaseDate":{"$date":"2019-04-17T00:00:00.000Z"},"Genre":"Drama","Distributor":"Fox","Runtime":"1 hrs. 56 min.","MPAARating":"PG"}
{"_id":{"$oid":"5c98d5bae2939d0fe0b966cb"},"ProductionBudget":"N/A","Movie":"Kalank","ReleaseDate":{"$date":"2019-04-17T00:00:00.000Z"},"Genre":"Drama","Distributor":"FIP","Runtime":"N/A","MPAARating":"Unrated"}
{"_id":{"$oid":"5c98d5bce2939d0fe0b966cc"},"ProductionBudget":"N/A","Movie":"Penguins (Disneynature)","ReleaseDate":{"$date":"2019-04-17T00:00:00.000Z"},"Genre":"Documentary","Distributor":"Buena Vista","Runtime":"1 hrs. 12 min.","MPAARating":"G"}
{"_id":{"$oid":"5c98d5bee2939d0fe0b966cd"},"ProductionBudget":"N/A","Movie":"RiffTrax Live: Octaman","ReleaseDate":{"$date":"2019-04-18T00:00:00.000Z"},"Genre":"Comedy","Distributor":"Fathom","Runtime":"2 hrs. 0 min.","MPAARating":"Unrated"}
{"_id":{"$oid":"5c98d5c0e2939d0fe0b966ce"},"ProductionBudget":"N/A","Movie":"The Curse of La Llorona","ReleaseDate":{"$date":"2019-04-19T00:00:00.000Z"},"Genre":"Horror","Distributor":"Warner Bros. (New Line)","Runtime":"1 hrs. 33 min.","MPAARating":"R"}
{"_id":{"$oid":"5c98d5c3e2939d0fe0b966cf"},"ProductionBudget":"N/A","Movie":"Fast Color","ReleaseDate":{"$date":"2019-04-19T00:00:00.000Z"},"Genre":"Drama","Distributor":"Lionsgate","Runtime":"N/A","MPAARating":"Not Yet Rated"}
{"_id":{"$oid":"5c98d5c4e2939d0fe0b966d0"},"ProductionBudget":"N/A","Movie":"High on the Hog","ReleaseDate":{"$date":"2019-04-19T00:00:00.000Z"},"Genre":"Action / Crime","Distributor":"Indican","Runtime":"1 hrs. 25 min.","MPAARating":"Unrated"}
{"_id":{"$oid":"5c98d5c7e2939d0fe0b966d1"},"ProductionBudget":"N/A","Movie":"Little Woods","ReleaseDate":{"$date":"2019-04-19T00:00:00.000Z"},"Genre":"Drama","Distributor":"Neon","Runtime":"1 hrs. 43 min.","MPAARating":"R"}
{"_id":{"$oid":"5c98d5c8e2939d0fe0b966d2"},"ProductionBudget":"N/A","Movie":"Meanest Man in Texas","ReleaseDate":{"$date":"2019-04-19T00:00:00.000Z"},"Genre":"Drama","Distributor":"Ammo Content","Runtime":"1 hrs. 45 min.","MPAARating":"Not Yet Rated"}
{"_id":{"$oid":"5c98d5cbe2939d0fe0b966d3"},"ProductionBudget":"N/A","Movie":"Rafiki","ReleaseDate":{"$date":"2019-04-19T00:00:00.000Z"},"Genre":"Drama","Distributor":"Film Movement","Runtime":"1 hrs. 23 min.","MPAARating":"Unrated"}
{"_id":{"$oid":"5c98d5d4e2939d0fe0b966d4"},"ProductionBudget":"N/A","Movie":"Bright Ones","ReleaseDate":{"$date":"2019-04-22T00:00:00.000Z"},"Genre":"Musical","Distributor":"Fathom","Runtime":"1 hrs. 55 min.","MPAARating":"PG"}
{"_id":{"$oid":"5c98d5d7e2939d0fe0b966d5"},"ProductionBudget":"N/A","Movie":"The White Crow","ReleaseDate":{"$date":"2019-04-26T00:00:00.000Z"},"Genre":"Drama","Distributor":"Sony Classics","Runtime":"2 hrs. 2 min.","MPAARating":"R"}
{"_id":{"$oid":"5c98d5d8e2939d0fe0b966d6"},"ProductionBudget":"N/A","Movie":"Kingdom Men Rising","ReleaseDate":{"$date":"2019-04-29T00:00:00.000Z"},"Genre":"Documentary","Distributor":"Fathom","Runtime":"1 hrs. 40 min.","MPAARating":"Unrated"}
{"_id":{"$oid":"5c98d5d9e2939d0fe0b966d7"},"ProductionBudget":"N/A","Movie":"Bolden","ReleaseDate":{"$date":"2019-05-03T00:00:00.000Z"},"Genre":"Drama","Distributor":"Abramorama","Runtime":"1 hrs. 41 min.","MPAARating":"R"}
{"_id":{"$oid":"5c98d5dbe2939d0fe0b966d8"},"ProductionBudget":"N/A","Movie":"The Intruder (2019)","ReleaseDate":{"$date":"2019-05-03T00:00:00.000Z"},"Genre":"Thriller","Distributor":"Sony / Screen Gems","Runtime":"N/A","MPAARating":"Not Yet Rated"}
{"_id":{"$oid":"5c98d5dce2939d0fe0b966d9"},"ProductionBudget":"N/A","Movie":"Long Shot","ReleaseDate":{"$date":"2019-05-03T00:00:00.000Z"},"Genre":"Comedy","Distributor":"Lionsgate/Summit","Runtime":"N/A","MPAARating":"Not Yet Rated"}
{"_id":{"$oid":"5c98d5dfe2939d0fe0b966da"},"ProductionBudget":"N/A","Movie":"Meeting Gorbachev","ReleaseDate":{"$date":"2019-05-03T00:00:00.000Z"},"Genre":"Documentary","Distributor":"The Orchard","Runtime":"1 hrs. 30 min.","MPAARating":"Unknown"}
{"_id":{"$oid":"5c98d5e1e2939d0fe0b966dc"},"ProductionBudget":"N/A","Movie":"Uglydolls","ReleaseDate":{"$date":"2019-05-03T00:00:00.000Z"},"Genre":"Animation","Distributor":"STX Entertainment","Runtime":"N/A","MPAARating":"Not Yet Rated"}
{"_id":{"$oid":"5c98d5e9e2939d0fe0b966dd"},"ProductionBudget":"N/A","Movie":"Biggest Little Farm","ReleaseDate":{"$date":"2019-05-10T00:00:00.000Z"},"Genre":"Documentary","Distributor":"Neon","Runtime":"1 hrs. 31 min.","MPAARating":"Not Yet Rated"}
{"_id":{"$oid":"5c98d5ebe2939d0fe0b966de"},"ProductionBudget":"N/A","Movie":"Detective Pikachu","ReleaseDate":{"$date":"2019-05-10T00:00:00.000Z"},"Genre":"Family","Distributor":"Warner Bros.","Runtime":"N/A","MPAARating":"PG"}
{"_id":{"$oid":"5c98d5ede2939d0fe0b966df"},"ProductionBudget":"N/A","Movie":"The Hustle","ReleaseDate":{"$date":"2019-05-10T00:00:00.000Z"},"Genre":"Comedy","Distributor":"United Artists Releasing","Runtime":"N/A","MPAARating":"PG-13"}
{"_id":{"$oid":"5c98d5fde2939d0fe0b966e0"},"ProductionBudget":"N/A","Movie":"Poms","ReleaseDate":{"$date":"2019-05-10T00:00:00.000Z"},"Genre":"Comedy","Distributor":"STX Entertainment","Runtime":"N/A","MPAARating":"Not Yet Rated"}
{"_id":{"$oid":"5c98d600e2939d0fe0b966e1"},"ProductionBudget":"N/A","Movie":"Tolkien","ReleaseDate":{"$date":"2019-05-10T00:00:00.000Z"},"Genre":"Unknown","Distributor":"Fox Searchlight","Runtime":"N/A","MPAARating":"Unknown"}
{"_id":{"$oid":"5c98d603e2939d0fe0b966e2"},"ProductionBudget":"N/A","Movie":"A Dog's Journey","ReleaseDate":{"$date":"2019-05-17T00:00:00.000Z"},"Genre":"Drama","Distributor":"Universal","Runtime":"N/A","MPAARating":"Not Yet Rated"}
{"_id":{"$oid":"5c98d606e2939d0fe0b966e3"},"ProductionBudget":"N/A","Movie":"John Wick: Chapter 3 - Parabellum","ReleaseDate":{"$date":"2019-05-17T00:00:00.000Z"},"Genre":"Action","Distributor":"Lionsgate/Summit","Runtime":"N/A","MPAARating":"Not Yet Rated"}
{"_id":{"$oid":"5c98d608e2939d0fe0b966e4"},"ProductionBudget":"N/A","Movie":"The Souvenir","ReleaseDate":{"$date":"2019-05-17T00:00:00.000Z"},"Genre":"Drama","Distributor":"A24","Runtime":"1 hrs. 55 min.","MPAARating":"Not Yet Rated"}
{"_id":{"$oid":"5c98d60ae2939d0fe0b966e5"},"ProductionBudget":"N/A","Movie":"The Sun Is Also a Star","ReleaseDate":{"$date":"2019-05-17T00:00:00.000Z"},"Genre":"Drama","Distributor":"Warner Bros.","Runtime":"N/A","MPAARating":"PG-13"}
{"_id":{"$oid":"5c98d60be2939d0fe0b966e6"},"ProductionBudget":"N/A","Movie":"Trial by Fire","ReleaseDate":{"$date":"2019-05-17T00:00:00.000Z"},"Genre":"Drama","Distributor":"Roadside Attractions","Runtime":"2 hrs. 7 min.","MPAARating":"Not Yet Rated"}
{"_id":{"$oid":"5c98d60ce2939d0fe0b966e7"},"ProductionBudget":"N/A","Movie":"Ad Astra","ReleaseDate":{"$date":"2019-05-24T00:00:00.000Z"},"Genre":"Sci-Fi Thriller","Distributor":"Fox","Runtime":"N/A","MPAARating":"Not Yet Rated"}
{"_id":{"$oid":"5c98d60ee2939d0fe0b966e8"},"ProductionBudget":"N/A","Movie":"Aladdin (2019)","ReleaseDate":{"$date":"2019-05-24T00:00:00.000Z"},"Genre":"Fantasy","Distributor":"Buena Vista","Runtime":"N/A","MPAARating":"Unknown"}
{"_id":{"$oid":"5c98d612e2939d0fe0b966e9"},"ProductionBudget":"N/A","Movie":"Booksmart","ReleaseDate":{"$date":"2019-05-24T00:00:00.000Z"},"Genre":"Comedy","Distributor":"United Artists Releasing","Runtime":"1 hrs. 45 min.","MPAARating":"Not Yet Rated"}
{"_id":{"$oid":"5c98d614e2939d0fe0b966ea"},"ProductionBudget":"N/A","Movie":"Brightburn","ReleaseDate":{"$date":"2019-05-24T00:00:00.000Z"},"Genre":"Horror","Distributor":"Sony / Screen Gems","Runtime":"N/A","MPAARating":"Not Yet Rated"}
{"_id":{"$oid":"5c98d615e2939d0fe0b966eb"},"ProductionBudget":"N/A","Movie":"Echo in the Canyon","ReleaseDate":{"$date":"2019-05-24T00:00:00.000Z"},"Genre":"Documentary","Distributor":"Greenwich","Runtime":"1 hrs. 22 min.","MPAARating":"Unrated"}
{"_id":{"$oid":"5c98d616e2939d0fe0b966ec"},"ProductionBudget":"N/A","Movie":"Halston","ReleaseDate":{"$date":"2019-05-24T00:00:00.000Z"},"Genre":"Documentary","Distributor":"The Orchard","Runtime":"1 hrs. 45 min.","MPAARating":"Unrated"}
{"_id":{"$oid":"5c98d619e2939d0fe0b966ed"},"ProductionBudget":"N/A","Movie":"The Tomorrow Man","ReleaseDate":{"$date":"2019-05-24T00:00:00.000Z"},"Genre":"Romance","Distributor":"Bleecker Street","Runtime":"1 hrs. 34 min.","MPAARating":"PG-13"}
{"_id":{"$oid":"5c98d61ae2939d0fe0b966ee"},"ProductionBudget":"N/A","Movie":"Godzilla: King of the Monsters","ReleaseDate":{"$date":"2019-05-31T00:00:00.000Z"},"Genre":"Sci-Fi Action","Distributor":"Warner Bros.","Runtime":"N/A","MPAARating":"PG-13"}
{"_id":{"$oid":"5c98d61de2939d0fe0b966ef"},"ProductionBudget":"N/A","Movie":"Ma","ReleaseDate":{"$date":"2019-05-31T00:00:00.000Z"},"Genre":"Thriller","Distributor":"Universal","Runtime":"N/A","MPAARating":"R"}
{"_id":{"$oid":"5c98d61fe2939d0fe0b966f0"},"ProductionBudget":"N/A","Movie":"Rocketman","ReleaseDate":{"$date":"2019-05-31T00:00:00.000Z"},"Genre":"Musical","Distributor":"Paramount","Runtime":"N/A","MPAARating":"Not Yet Rated"}
{"_id":{"$oid":"5c98d620e2939d0fe0b966f1"},"ProductionBudget":"N/A","Movie":"RiffTrax Live: Star Raiders","ReleaseDate":{"$date":"2019-06-06T00:00:00.000Z"},"Genre":"Comedy","Distributor":"Fathom","Runtime":"2 hrs. 0 min.","MPAARating":"Unrated"}
{"_id":{"$oid":"5c98d622e2939d0fe0b966f2"},"ProductionBudget":"N/A","Movie":"Dark Phoenix","ReleaseDate":{"$date":"2019-06-07T00:00:00.000Z"},"Genre":"Action","Distributor":"Fox","Runtime":"N/A","MPAARating":"Not Yet Rated"}
{"_id":{"$oid":"5c98d623e2939d0fe0b966f3"},"ProductionBudget":"N/A","Movie":"Late Night","ReleaseDate":{"$date":"2019-06-07T00:00:00.000Z"},"Genre":"Comedy / Drama","Distributor":"Amazon Studios","Runtime":"1 hrs. 40 min.","MPAARating":"Not Yet Rated"}
{"_id":{"$oid":"5c98d626e2939d0fe0b966f4"},"ProductionBudget":"N/A","Movie":"The Secret Life of Pets 2","ReleaseDate":{"$date":"2019-06-07T00:00:00.000Z"},"Genre":"Animation","Distributor":"Universal","Runtime":"N/A","MPAARating":"PG"}
{"_id":{"$oid":"5c98d629e2939d0fe0b966f5"},"ProductionBudget":"N/A","Movie":"This One's for the Ladies","ReleaseDate":{"$date":"2019-06-07T00:00:00.000Z"},"Genre":"Documentary","Distributor":"Neon","Runtime":"1 hrs. 22 min.","MPAARating":"Unrated"}
{"_id":{"$oid":"5c98d62de2939d0fe0b966f6"},"ProductionBudget":"N/A","Movie":"The Last Black Man in San Francisco","ReleaseDate":{"$date":"2019-06-14T00:00:00.000Z"},"Genre":"Drama","Distributor":"A24","Runtime":"2 hrs. 0 min.","MPAARating":"Not Yet Rated"}
{"_id":{"$oid":"5c98d62ee2939d0fe0b966f7"},"ProductionBudget":"N/A","Movie":"Men in Black International","ReleaseDate":{"$date":"2019-06-14T00:00:00.000Z"},"Genre":"Sci-Fi Comedy","Distributor":"Sony / Columbia","Runtime":"N/A","MPAARating":"Not Yet Rated"}
{"_id":{"$oid":"5c98d62fe2939d0fe0b966f8"},"ProductionBudget":"N/A","Movie":"Shaft (2019)","ReleaseDate":{"$date":"2019-06-14T00:00:00.000Z"},"Genre":"Action","Distributor":"Warner Bros. (New Line)","Runtime":"N/A","MPAARating":"R"}
{"_id":{"$oid":"5c98d632e2939d0fe0b966f9"},"ProductionBudget":"N/A","Movie":"Wild Rose","ReleaseDate":{"$date":"2019-06-14T00:00:00.000Z"},"Genre":"Comedy / Drama","Distributor":"Neon","Runtime":"1 hrs. 41 min.","MPAARating":"Not Yet Rated"}
{"_id":{"$oid":"5c98d634e2939d0fe0b966fa"},"ProductionBudget":"N/A","Movie":"Emanuel","ReleaseDate":{"$date":"2019-06-17T00:00:00.000Z"},"Genre":"Documentary","Distributor":"Fathom","Runtime":"2 hrs. 30 min.","MPAARating":"Unrated"}
{"_id":{"$oid":"5c98d635e2939d0fe0b966fb"},"ProductionBudget":"N/A","Movie":"The Art of Self Defense","ReleaseDate":{"$date":"2019-06-21T00:00:00.000Z"},"Genre":"Comedy","Distributor":"Bleecker Street","Runtime":"1 hrs. 44 min.","MPAARating":"R"}
{"_id":{"$oid":"5c98d636e2939d0fe0b966fc"},"ProductionBudget":"N/A","Movie":"Child's Play (2019)","ReleaseDate":{"$date":"2019-06-21T00:00:00.000Z"},"Genre":"Horror","Distributor":"United Artists Releasing","Runtime":"N/A","MPAARating":"Not Yet Rated"}
{"_id":{"$oid":"5c98d638e2939d0fe0b966fd"},"ProductionBudget":"N/A","Movie":"Round of Your Life","ReleaseDate":{"$date":"2019-06-21T00:00:00.000Z"},"Genre":"Sports Drama","Distributor":"Ammo Content","Runtime":"1 hrs. 31 min.","MPAARating":"Unrated"}
{"_id":{"$oid":"5c98d63ae2939d0fe0b966fe"},"ProductionBudget":"N/A","Movie":"Them That Follow","ReleaseDate":{"$date":"2019-06-21T00:00:00.000Z"},"Genre":"Thriller","Distributor":"The Orchard","Runtime":"1 hrs. 38 min.","MPAARating":"R"}
{"_id":{"$oid":"5c98d643e2939d0fe0b966ff"},"ProductionBudget":"N/A","Movie":"The Other Side of Heaven 2: Fire of Faith","ReleaseDate":{"$date":"2019-06-28T00:00:00.000Z"},"Genre":"Drama","Distributor":"ArtAffects","Runtime":"1 hrs. 50 min.","MPAARating":"Not Yet Rated"}
{"_id":{"$oid":"5c98d645e2939d0fe0b96700"},"ProductionBudget":"N/A","Movie":"Yesterday","ReleaseDate":{"$date":"2019-06-28T00:00:00.000Z"},"Genre":"Comedy","Distributor":"Universal","Runtime":"1 hrs. 52 min.","MPAARating":"PG-13"}
{"_id":{"$oid":"5c98d647e2939d0fe0b96701"},"ProductionBudget":"N/A","Movie":"Spider-Man: Far from Home","ReleaseDate":{"$date":"2019-07-05T00:00:00.000Z"},"Genre":"Action / Adventure","Distributor":"Sony / Columbia","Runtime":"N/A","MPAARating":"Not Yet Rated"}
{"_id":{"$oid":"5c98d648e2939d0fe0b96702"},"ProductionBudget":"N/A","Movie":"17 Bridges","ReleaseDate":{"$date":"2019-07-12T00:00:00.000Z"},"Genre":"Crime Thriller","Distributor":"STX Entertainment","Runtime":"N/A","MPAARating":"Not Yet Rated"}
{"_id":{"$oid":"5c98d64be2939d0fe0b96703"},"ProductionBudget":"N/A","Movie":"Crawl","ReleaseDate":{"$date":"2019-07-12T00:00:00.000Z"},"Genre":"Horror","Distributor":"Paramount","Runtime":"N/A","MPAARating":"Unknown"}
{"_id":{"$oid":"5c98d64de2939d0fe0b96704"},"ProductionBudget":"N/A","Movie":"The Farewell","ReleaseDate":{"$date":"2019-07-12T00:00:00.000Z"},"Genre":"Comedy / Drama","Distributor":"A24","Runtime":"1 hrs. 38 min.","MPAARating":"Not Yet Rated"}
{"_id":{"$oid":"5c98d64ee2939d0fe0b96705"},"ProductionBudget":"N/A","Movie":"Stuber","ReleaseDate":{"$date":"2019-07-12T00:00:00.000Z"},"Genre":"Action Comedy","Distributor":"Fox","Runtime":"N/A","MPAARating":"Not Yet Rated"}
{"_id":{"$oid":"5c98d64fe2939d0fe0b96706"},"ProductionBudget":"N/A","Movie":"David Crosby: Remember My Name","ReleaseDate":{"$date":"2019-07-19T00:00:00.000Z"},"Genre":"Documentary","Distributor":"Sony Classics","Runtime":"1 hrs. 35 min.","MPAARating":"Unrated"}
{"_id":{"$oid":"5c98d651e2939d0fe0b96707"},"ProductionBudget":"N/A","Movie":"The Lion King (2019)","ReleaseDate":{"$date":"2019-07-19T00:00:00.000Z"},"Genre":"Action / Adventure","Distributor":"Buena Vista","Runtime":"N/A","MPAARating":"Not Yet Rated"}
{"_id":{"$oid":"5c98d653e2939d0fe0b96708"},"ProductionBudget":"N/A","Movie":"The Boy 2","ReleaseDate":{"$date":"2019-07-26T00:00:00.000Z"},"Genre":"Horror Thriller","Distributor":"STX Entertainment","Runtime":"N/A","MPAARating":"Not Yet Rated"}
{"_id":{"$oid":"5c98d655e2939d0fe0b96709"},"ProductionBudget":"N/A","Movie":"Once Upon a Time in Hollywood","ReleaseDate":{"$date":"2019-07-26T00:00:00.000Z"},"Genre":"Unknown","Distributor":"Sony / Columbia","Runtime":"N/A","MPAARating":"Not Yet Rated"}
{"_id":{"$oid":"5c98d656e2939d0fe0b9670a"},"ProductionBudget":"N/A","Movie":"Dora and the Lost City of Gold","ReleaseDate":{"$date":"2019-08-02T00:00:00.000Z"},"Genre":"Family","Distributor":"Paramount","Runtime":"N/A","MPAARating":"Not Yet Rated"}
{"_id":{"$oid":"5c98d658e2939d0fe0b9670b"},"ProductionBudget":"N/A","Movie":"Fast \u0026 Furious Presents: Hobbs \u0026 Shaw","ReleaseDate":{"$date":"2019-08-02T00:00:00.000Z"},"Genre":"Action","Distributor":"Universal","Runtime":"N/A","MPAARating":"Not Yet Rated"}
{"_id":{"$oid":"5c98d65be2939d0fe0b9670c"},"ProductionBudget":"N/A","Movie":"Luce","ReleaseDate":{"$date":"2019-08-02T00:00:00.000Z"},"Genre":"Drama / Thriller","Distributor":"Neon","Runtime":"1 hrs. 50 min.","MPAARating":"Not Yet Rated"}
{"_id":{"$oid":"5c98d65de2939d0fe0b9670d"},"ProductionBudget":"N/A","Movie":"New Mutants","ReleaseDate":{"$date":"2019-08-02T00:00:00.000Z"},"Genre":"Action","Distributor":"Fox","Runtime":"N/A","MPAARating":"Not Yet Rated"}
{"_id":{"$oid":"5c98d672e2939d0fe0b9670e"},"ProductionBudget":"N/A","Movie":"Artemis Fowl","ReleaseDate":{"$date":"2019-08-09T00:00:00.000Z"},"Genre":"Action / Adventure","Distributor":"Buena Vista","Runtime":"N/A","MPAARating":"Not Yet Rated"}
{"_id":{"$oid":"5c98d673e2939d0fe0b9670f"},"ProductionBudget":"N/A","Movie":"Brian Banks","ReleaseDate":{"$date":"2019-08-09T00:00:00.000Z"},"Genre":"Drama","Distributor":"Bleecker Street","Runtime":"N/A","MPAARating":"PG-13"}
{"_id":{"$oid":"5c98d679e2939d0fe0b96710"},"ProductionBudget":"N/A","Movie":"The Kitchen (2019)","ReleaseDate":{"$date":"2019-08-09T00:00:00.000Z"},"Genre":"Action / Crime","Distributor":"Warner Bros. (New Line)","Runtime":"N/A","MPAARating":"R"}
{"_id":{"$oid":"5c98d67be2939d0fe0b96711"},"ProductionBudget":"N/A","Movie":"Midsommar","ReleaseDate":{"$date":"2019-08-09T00:00:00.000Z"},"Genre":"Horror","Distributor":"A24","Runtime":"N/A","MPAARating":"Not Yet Rated"}
{"_id":{"$oid":"5c98d67ce2939d0fe0b96712"},"ProductionBudget":"N/A","Movie":"Scary Stories to Tell in the Dark","ReleaseDate":{"$date":"2019-08-09T00:00:00.000Z"},"Genre":"Horror Thriller","Distributor":"Lionsgate","Runtime":"N/A","MPAARating":"Not Yet Rated"}
{"_id":{"$oid":"5c98d67de2939d0fe0b96713"},"ProductionBudget":"N/A","Movie":"Where'd You Go, Bernadette","ReleaseDate":{"$date":"2019-08-09T00:00:00.000Z"},"Genre":"Comedy / Drama","Distributor":"United Artists Releasing","Runtime":"N/A","MPAARating":"PG-13"}
{"_id":{"$oid":"5c98d67fe2939d0fe0b96714"},"ProductionBudget":"N/A","Movie":"Blinded By the Light","ReleaseDate":{"$date":"2019-08-14T00:00:00.000Z"},"Genre":"Comedy / Drama","Distributor":"Warner Bros.","Runtime":"1 hrs. 54 min.","MPAARating":"Not Yet Rated"}
{"_id":{"$oid":"5c98d681e2939d0fe0b96715"},"ProductionBudget":"N/A","Movie":"RiffTrax Live: Giant Spider Invasion","ReleaseDate":{"$date":"2019-08-15T00:00:00.000Z"},"Genre":"Comedy","Distributor":"Fathom","Runtime":"2 hrs. 0 min.","MPAARating":"Unrated"}
{"_id":{"$oid":"5c98d682e2939d0fe0b96716"},"ProductionBudget":"N/A","Movie":"47 Meters Down: Uncaged","ReleaseDate":{"$date":"2019-08-16T00:00:00.000Z"},"Genre":"Horror Thriller","Distributor":"Entertainment Studios","Runtime":"N/A","MPAARating":"Not Yet Rated"}
{"_id":{"$oid":"5c98d684e2939d0fe0b96717"},"ProductionBudget":"N/A","Movie":"The Angry Birds Movie 2 in 3D","ReleaseDate":{"$date":"2019-08-16T00:00:00.000Z"},"Genre":"Animation","Distributor":"Sony / Columbia","Runtime":"N/A","MPAARating":"Not Yet Rated"}
{"_id":{"$oid":"5c98d686e2939d0fe0b96718"},"ProductionBudget":"N/A","Movie":"Aquarela","ReleaseDate":{"$date":"2019-08-16T00:00:00.000Z"},"Genre":"Documentary","Distributor":"Sony Classics","Runtime":"1 hrs. 29 min.","MPAARating":"PG"}
{"_id":{"$oid":"5c98d688e2939d0fe0b96719"},"ProductionBudget":"N/A","Movie":"Good Boys","ReleaseDate":{"$date":"2019-08-16T00:00:00.000Z"},"Genre":"Comedy","Distributor":"Universal","Runtime":"N/A","MPAARating":"R"}
{"_id":{"$oid":"5c98d689e2939d0fe0b9671a"},"ProductionBudget":"N/A","Movie":"The Informer","ReleaseDate":{"$date":"2019-08-16T00:00:00.000Z"},"Genre":"Crime Drama","Distributor":"Aviron","Runtime":"1 hrs. 53 min.","MPAARating":"Not Yet Rated"}
{"_id":{"$oid":"5c98d68be2939d0fe0b9671b"},"ProductionBudget":"N/A","Movie":"PLAYMOBIL","ReleaseDate":{"$date":"2019-08-16T00:00:00.000Z"},"Genre":"Animation","Distributor":"Global Road","Runtime":"N/A","MPAARating":"Not Yet Rated"}
{"_id":{"$oid":"5c98d68ce2939d0fe0b9671c"},"ProductionBudget":"N/A","Movie":"Angel has Fallen","ReleaseDate":{"$date":"2019-08-23T00:00:00.000Z"},"Genre":"Action","Distributor":"Lionsgate","Runtime":"N/A","MPAARating":"Not Yet Rated"}
{"_id":{"$oid":"5c98d690e2939d0fe0b9671d"},"ProductionBudget":"N/A","Movie":"Overcomer","ReleaseDate":{"$date":"2019-08-23T00:00:00.000Z"},"Genre":"Drama","Distributor":"Sony / AFFIRM Films","Runtime":"N/A","MPAARating":"Not Yet Rated"}
{"_id":{"$oid":"5c98d695e2939d0fe0b9671e"},"ProductionBudget":"N/A","Movie":"Las Pildoras de Mi Novio (My Boyfriend's Meds)","ReleaseDate":{"$date":"2019-08-30T00:00:00.000Z"},"Genre":"Comedy","Distributor":"Pantelion","Runtime":"N/A","MPAARating":"Not Yet Rated"}
{"_id":{"$oid":"5c98d697e2939d0fe0b9671f"},"ProductionBudget":"N/A","Movie":"It: Chapter 2","ReleaseDate":{"$date":"2019-09-06T00:00:00.000Z"},"Genre":"Horror","Distributor":"Warner Bros. (New Line)","Runtime":"N/A","MPAARating":"Not Yet Rated"}
{"_id":{"$oid":"5c98d69ae2939d0fe0b96720"},"ProductionBudget":"N/A","Movie":"The Goldfinch","ReleaseDate":{"$date":"2019-09-13T00:00:00.000Z"},"Genre":"Drama","Distributor":"Warner Bros.","Runtime":"N/A","MPAARating":"R"}
{"_id":{"$oid":"5c98d69ce2939d0fe0b96721"},"ProductionBudget":"N/A","Movie":"Spies in Disguise","ReleaseDate":{"$date":"2019-09-13T00:00:00.000Z"},"Genre":"Animation","Distributor":"Fox","Runtime":"N/A","MPAARating":"Not Yet Rated"}
{"_id":{"$oid":"5c98d69de2939d0fe0b96722"},"ProductionBudget":"N/A","Movie":"Black and Blue","ReleaseDate":{"$date":"2019-09-20T00:00:00.000Z"},"Genre":"Action","Distributor":"Sony / Screen Gems","Runtime":"N/A","MPAARating":"Not Yet Rated"}
{"_id":{"$oid":"5c98d69fe2939d0fe0b96723"},"ProductionBudget":"N/A","Movie":"Downton Abbey","ReleaseDate":{"$date":"2019-09-20T00:00:00.000Z"},"Genre":"Drama","Distributor":"Focus Features","Runtime":"N/A","MPAARating":"Not Yet Rated"}
{"_id":{"$oid":"5c98d6a0e2939d0fe0b96724"},"ProductionBudget":"N/A","Movie":"Rambo: Last Blood","ReleaseDate":{"$date":"2019-09-20T00:00:00.000Z"},"Genre":"Action","Distributor":"Lionsgate","Runtime":"N/A","MPAARating":"Not Yet Rated"}
{"_id":{"$oid":"5c98d6a1e2939d0fe0b96725"},"ProductionBudget":"N/A","Movie":"Abominable","ReleaseDate":{"$date":"2019-09-27T00:00:00.000Z"},"Genre":"Animation","Distributor":"Universal","Runtime":"N/A","MPAARating":"Not Yet Rated"}
{"_id":{"$oid":"5c98d6a4e2939d0fe0b96726"},"ProductionBudget":"N/A","Movie":"The Art of Racing in the Rain","ReleaseDate":{"$date":"2019-09-27T00:00:00.000Z"},"Genre":"Drama","Distributor":"Fox","Runtime":"N/A","MPAARating":"PG"}
{"_id":{"$oid":"5c98d6a6e2939d0fe0b96727"},"ProductionBudget":"N/A","Movie":"Judy","ReleaseDate":{"$date":"2019-09-27T00:00:00.000Z"},"Genre":"Drama","Distributor":"Roadside Attractions","Runtime":"1 hrs. 58 min.","MPAARating":"Not Yet Rated"}
{"_id":{"$oid":"5c98d6a8e2939d0fe0b96728"},"ProductionBudget":"N/A","Movie":"Untitled Blumhouse Productions Project I (2019)","ReleaseDate":{"$date":"2019-09-27T00:00:00.000Z"},"Genre":"Horror","Distributor":"Universal","Runtime":"N/A","MPAARating":"Not Yet Rated"}
{"_id":{"$oid":"5c98d6a9e2939d0fe0b96729"},"ProductionBudget":"N/A","Movie":"Joker (2019)","ReleaseDate":{"$date":"2019-10-04T00:00:00.000Z"},"Genre":"Action / Crime","Distributor":"Warner Bros.","Runtime":"N/A","MPAARating":"Not Yet Rated"}
{"_id":{"$oid":"5c98d6aae2939d0fe0b9672a"},"ProductionBudget":"N/A","Movie":"The Woman in the Window (2019)","ReleaseDate":{"$date":"2019-10-04T00:00:00.000Z"},"Genre":"Thriller","Distributor":"Fox","Runtime":"N/A","MPAARating":"Not Yet Rated"}
{"_id":{"$oid":"5c98d6ace2939d0fe0b9672b"},"ProductionBudget":"N/A","Movie":"Gemini Man","ReleaseDate":{"$date":"2019-10-11T00:00:00.000Z"},"Genre":"Sci-Fi","Distributor":"Paramount","Runtime":"N/A","MPAARating":"Not Yet Rated"}
{"_id":{"$oid":"5c98d6ade2939d0fe0b9672c"},"ProductionBudget":"N/A","Movie":"Zombieland 2: Double Tap","ReleaseDate":{"$date":"2019-10-11T00:00:00.000Z"},"Genre":"Adventure Comedy","Distributor":"Sony / Columbia","Runtime":"N/A","MPAARating":"Not Yet Rated"}
{"_id":{"$oid":"5c98d6afe2939d0fe0b9672d"},"ProductionBudget":"N/A","Movie":"The Addams Family (2019)","ReleaseDate":{"$date":"2019-10-18T00:00:00.000Z"},"Genre":"Animation","Distributor":"United Artists Releasing","Runtime":"N/A","MPAARating":"Not Yet Rated"}
{"_id":{"$oid":"5c98d6b1e2939d0fe0b9672e"},"ProductionBudget":"N/A","Movie":"The Hunt (2019)","ReleaseDate":{"$date":"2019-10-18T00:00:00.000Z"},"Genre":"Action Thriller","Distributor":"Universal","Runtime":"N/A","MPAARating":"Not Yet Rated"}
{"_id":{"$oid":"5c98d6b2e2939d0fe0b9672f"},"ProductionBudget":"N/A","Movie":"Maleficent: Mistress of Evil","ReleaseDate":{"$date":"2019-10-18T00:00:00.000Z"},"Genre":"Fantasy","Distributor":"Buena Vista","Runtime":"N/A","MPAARating":"Not Yet Rated"}
{"_id":{"$oid":"5c98d6b5e2939d0fe0b96730"},"ProductionBudget":"N/A","Movie":"Bad Trip","ReleaseDate":{"$date":"2019-10-25T00:00:00.000Z"},"Genre":"Comedy","Distributor":"United Artists Releasing","Runtime":"N/A","MPAARating":"Not Yet Rated"}
{"_id":{"$oid":"5c98d6b8e2939d0fe0b96731"},"ProductionBudget":"N/A","Movie":"Untitled Aviron Horror","ReleaseDate":{"$date":"2019-10-25T00:00:00.000Z"},"Genre":"Horror","Distributor":"Aviron","Runtime":"N/A","MPAARating":"Not Yet Rated"}
{"_id":{"$oid":"5c98d6b9e2939d0fe0b96732"},"ProductionBudget":"N/A","Movie":"Arctic Dogs","ReleaseDate":{"$date":"2019-11-01T00:00:00.000Z"},"Genre":"Animation","Distributor":"Entertainment Studios","Runtime":"1 hrs. 33 min.","MPAARating":"PG"}
{"_id":{"$oid":"5c98d6bbe2939d0fe0b96733"},"ProductionBudget":"N/A","Movie":"Charlie's Angels (2019)","ReleaseDate":{"$date":"2019-11-01T00:00:00.000Z"},"Genre":"Action","Distributor":"Sony / Columbia","Runtime":"N/A","MPAARating":"Not Yet Rated"}
{"_id":{"$oid":"5c98d6bce2939d0fe0b96734"},"ProductionBudget":"N/A","Movie":"Motherless Brooklyn","ReleaseDate":{"$date":"2019-11-01T00:00:00.000Z"},"Genre":"Crime Drama","Distributor":"Warner Bros.","Runtime":"N/A","MPAARating":"R"}
{"_id":{"$oid":"5c98d6bfe2939d0fe0b96735"},"ProductionBudget":"N/A","Movie":"Terminator: Dark Fate","ReleaseDate":{"$date":"2019-11-01T00:00:00.000Z"},"Genre":"Sci-Fi","Distributor":"Paramount","Runtime":"N/A","MPAARating":"Not Yet Rated"}
{"_id":{"$oid":"5c98d6c0e2939d0fe0b96736"},"ProductionBudget":"N/A","Movie":"Doctor Sleep","ReleaseDate":{"$date":"2019-11-08T00:00:00.000Z"},"Genre":"Horror Thriller","Distributor":"Warner Bros.","Runtime":"N/A","MPAARating":"Not Yet Rated"}
{"_id":{"$oid":"5c98d6c3e2939d0fe0b96737"},"ProductionBudget":"N/A","Movie":"Midway","ReleaseDate":{"$date":"2019-11-08T00:00:00.000Z"},"Genre":"Action Drama","Distributor":"Lionsgate/Summit","Runtime":"N/A","MPAARating":"Not Yet Rated"}
{"_id":{"$oid":"5c98d6c4e2939d0fe0b96738"},"ProductionBudget":"N/A","Movie":"Sonic The Hedgehog","ReleaseDate":{"$date":"2019-11-08T00:00:00.000Z"},"Genre":"Animation","Distributor":"Paramount","Runtime":"N/A","MPAARating":"Not Yet Rated"}
{"_id":{"$oid":"5c98d6c7e2939d0fe0b96739"},"ProductionBudget":"N/A","Movie":"Will Packer Comedy I (2019)","ReleaseDate":{"$date":"2019-11-08T00:00:00.000Z"},"Genre":"Comedy","Distributor":"Universal","Runtime":"N/A","MPAARating":"Not Yet Rated"}
{"_id":{"$oid":"5c98d6c9e2939d0fe0b9673a"},"ProductionBudget":"N/A","Movie":"The Good Liar","ReleaseDate":{"$date":"2019-11-15T00:00:00.000Z"},"Genre":"Drama","Distributor":"Warner Bros. (New Line)","Runtime":"N/A","MPAARating":"Not Yet Rated"}
{"_id":{"$oid":"5c98d6cae2939d0fe0b9673b"},"ProductionBudget":"N/A","Movie":"Last Christmas","ReleaseDate":{"$date":"2019-11-15T00:00:00.000Z"},"Genre":"Romantic Comedy","Distributor":"Universal","Runtime":"N/A","MPAARating":"Not Yet Rated"}
{"_id":{"$oid":"5c98d6cbe2939d0fe0b9673c"},"ProductionBudget":"N/A","Movie":"Untitled James Mangold","ReleaseDate":{"$date":"2019-11-15T00:00:00.000Z"},"Genre":"Drama","Distributor":"Fox","Runtime":"N/A","MPAARating":"Not Yet Rated"}
{"_id":{"$oid":"5c98d6cde2939d0fe0b9673d"},"ProductionBudget":"N/A","Movie":"A Beautiful Day in the Neighborhood","ReleaseDate":{"$date":"2019-11-22T00:00:00.000Z"},"Genre":"Drama","Distributor":"Sony / Columbia","Runtime":"N/A","MPAARating":"Not Yet Rated"}
{"_id":{"$oid":"5c98d6cee2939d0fe0b9673e"},"ProductionBudget":"N/A","Movie":"Frozen 2","ReleaseDate":{"$date":"2019-11-22T00:00:00.000Z"},"Genre":"Animation","Distributor":"Buena Vista","Runtime":"N/A","MPAARating":"Unknown"}
{"_id":{"$oid":"5c98d6cfe2939d0fe0b9673f"},"ProductionBudget":"N/A","Movie":"Rhythm Section","ReleaseDate":{"$date":"2019-11-22T00:00:00.000Z"},"Genre":"Action Thriller","Distributor":"Paramount","Runtime":"N/A","MPAARating":"Not Yet Rated"}
{"_id":{"$oid":"5c98d6d1e2939d0fe0b96740"},"ProductionBudget":"N/A","Movie":"Knives Out","ReleaseDate":{"$date":"2019-11-27T00:00:00.000Z"},"Genre":"Drama / Thriller","Distributor":"Lionsgate","Runtime":"N/A","MPAARating":"Not Yet Rated"}
{"_id":{"$oid":"5c98d6d2e2939d0fe0b96741"},"ProductionBudget":"N/A","Movie":"Queen \u0026 Slim","ReleaseDate":{"$date":"2019-11-27T00:00:00.000Z"},"Genre":"Romance","Distributor":"Universal","Runtime":"N/A","MPAARating":"Not Yet Rated"}
{"_id":{"$oid":"5c98d6d6e2939d0fe0b96742"},"ProductionBudget":"N/A","Movie":"Jumanji Sequel","ReleaseDate":{"$date":"2019-12-13T00:00:00.000Z"},"Genre":"Action Comedy","Distributor":"Sony / Columbia","Runtime":"N/A","MPAARating":"Not Yet Rated"}
{"_id":{"$oid":"5c98d6d7e2939d0fe0b96743"},"ProductionBudget":"N/A","Movie":"Untitled Blumhouse Productions Project II (2019)","ReleaseDate":{"$date":"2019-12-13T00:00:00.000Z"},"Genre":"Horror","Distributor":"Universal","Runtime":"N/A","MPAARating":"Not Yet Rated"}
{"_id":{"$oid":"5c98d6d8e2939d0fe0b96744"},"ProductionBudget":"N/A","Movie":"Masters of the Universe (2019)","ReleaseDate":{"$date":"2019-12-18T00:00:00.000Z"},"Genre":"Action / Adventure","Distributor":"Sony / Columbia","Runtime":"N/A","MPAARating":"Not Yet Rated"}
{"_id":{"$oid":"5c98d6d9e2939d0fe0b96745"},"ProductionBudget":"N/A","Movie":"Cats","ReleaseDate":{"$date":"2019-12-20T00:00:00.000Z"},"Genre":"Musical","Distributor":"Universal","Runtime":"N/A","MPAARating":"Not Yet Rated"}
{"_id":{"$oid":"5c98d6dbe2939d0fe0b96746"},"ProductionBudget":"N/A","Movie":"Star Wars: Episode IX","ReleaseDate":{"$date":"2019-12-20T00:00:00.000Z"},"Genre":"Sci-Fi Fantasy","Distributor":"Buena Vista","Runtime":"N/A","MPAARating":"Not Yet Rated"}
{"_id":{"$oid":"5c98d6e0e2939d0fe0b96747"},"ProductionBudget":"N/A","Movie":"Superintelligence","ReleaseDate":{"$date":"2019-12-20T00:00:00.000Z"},"Genre":"Action Comedy","Distributor":"Warner Bros. (New Line)","Runtime":"N/A","MPAARating":"Not Yet Rated"}
{"_id":{"$oid":"5c98d6e1e2939d0fe0b96748"},"ProductionBudget":"N/A","Movie":"Untitled Charles Randolph Film","ReleaseDate":{"$date":"2019-12-20T00:00:00.000Z"},"Genre":"Drama","Distributor":"Lionsgate","Runtime":"N/A","MPAARating":"Not Yet Rated"}
{"_id":{"$oid":"5c98d6e3e2939d0fe0b96749"},"ProductionBudget":"N/A","Movie":"1917","ReleaseDate":{"$date":"2019-12-25T00:00:00.000Z"},"Genre":"War","Distributor":"Universal","Runtime":"N/A","MPAARating":"Not Yet Rated"}
{"_id":{"$oid":"5c98d6e4e2939d0fe0b9674a"},"ProductionBudget":"N/A","Movie":"The Call of the Wild","ReleaseDate":{"$date":"2019-12-25T00:00:00.000Z"},"Genre":"Animation","Distributor":"Fox","Runtime":"N/A","MPAARating":"Not Yet Rated"}
{"_id":{"$oid":"5c98d6e6e2939d0fe0b9674b"},"ProductionBudget":"N/A","Movie":"Little Women (2019)","ReleaseDate":{"$date":"2019-12-25T00:00:00.000Z"},"Genre":"Drama","Distributor":"Sony / Columbia","Runtime":"N/A","MPAARating":"Not Yet Rated"}
{"_id":{"$oid":"5c98d6ebe2939d0fe0b9674d"},"ProductionBudget":"N/A","Movie":"Grudge (2019)","ReleaseDate":{"$date":"2020-01-03T00:00:00.000Z"},"Genre":"Horror","Distributor":"Sony / Columbia","Runtime":"N/A","MPAARating":"Not Yet Rated"}
{"_id":{"$oid":"5c98d6ece2939d0fe0b9674e"},"ProductionBudget":"N/A","Movie":"Untitled Blumhouse Productions Project V","ReleaseDate":{"$date":"2020-01-03T00:00:00.000Z"},"Genre":"Unknown","Distributor":"Universal","Runtime":"N/A","MPAARating":"Not Yet Rated"}
{"_id":{"$oid":"5c98d6efe2939d0fe0b9674f"},"ProductionBudget":"N/A","Movie":"Limited Partners","ReleaseDate":{"$date":"2020-01-10T00:00:00.000Z"},"Genre":"Comedy","Distributor":"Paramount","Runtime":"N/A","MPAARating":"Not Yet Rated"}
{"_id":{"$oid":"5c98d6f0e2939d0fe0b96750"},"ProductionBudget":"N/A","Movie":"Phil Lord and Chris Miller Produced Sony Pictures Animation Movie","ReleaseDate":{"$date":"2020-01-10T00:00:00.000Z"},"Genre":"Animation","Distributor":"Columbia","Runtime":"N/A","MPAARating":"Not Yet Rated"}
{"_id":{"$oid":"5c98d6f2e2939d0fe0b96751"},"ProductionBudget":"N/A","Movie":"Bad Boys for Life","ReleaseDate":{"$date":"2020-01-17T00:00:00.000Z"},"Genre":"Action / Crime","Distributor":"Sony / Columbia","Runtime":"N/A","MPAARating":"Not Yet Rated"}
{"_id":{"$oid":"5c98d6f3e2939d0fe0b96752"},"ProductionBudget":"N/A","Movie":"Just Mercy","ReleaseDate":{"$date":"2020-01-17T00:00:00.000Z"},"Genre":"Unknown","Distributor":"Warner Bros.","Runtime":"N/A","MPAARating":"Not Yet Rated"}
{"_id":{"$oid":"5c98d6f5e2939d0fe0b96753"},"ProductionBudget":"N/A","Movie":"The Voyage of Doctor Dolittle","ReleaseDate":{"$date":"2020-01-17T00:00:00.000Z"},"Genre":"Comedy","Distributor":"Universal","Runtime":"N/A","MPAARating":"Not Yet Rated"}
{"_id":{"$oid":"5c98d6f6e2939d0fe0b96754"},"ProductionBudget":"N/A","Movie":"Run (2020)","ReleaseDate":{"$date":"2020-01-24T00:00:00.000Z"},"Genre":"Thriller","Distributor":"Lionsgate/Summit","Runtime":"N/A","MPAARating":"Not Yet Rated"}
{"_id":{"$oid":"5c98d6f9e2939d0fe0b96755"},"ProductionBudget":"N/A","Movie":"The Turning","ReleaseDate":{"$date":"2020-01-24T00:00:00.000Z"},"Genre":"Thriller","Distributor":"Universal","Runtime":"N/A","MPAARating":"Not Yet Rated"}
{"_id":{"$oid":"5c98d6fbe2939d0fe0b96756"},"ProductionBudget":"N/A","Movie":"Birds of Prey (and the Fantabulous Emancipation of One Harley Quinn)","ReleaseDate":{"$date":"2020-02-07T00:00:00.000Z"},"Genre":"Action / Adventure","Distributor":"Warner Bros.","Runtime":"N/A","MPAARating":"Not Yet Rated"}
{"_id":{"$oid":"5c98d6fee2939d0fe0b96757"},"ProductionBudget":"N/A","Movie":"Peter Rabbit 2","ReleaseDate":{"$date":"2020-02-07T00:00:00.000Z"},"Genre":"Family","Distributor":"Sony / Columbia","Runtime":"N/A","MPAARating":"Not Yet Rated"}
{"_id":{"$oid":"5c98d701e2939d0fe0b96758"},"ProductionBudget":"N/A","Movie":"Nimona","ReleaseDate":{"$date":"2020-02-14T00:00:00.000Z"},"Genre":"Unknown","Distributor":"Fox","Runtime":"N/A","MPAARating":"Unknown"}
{"_id":{"$oid":"5c98d702e2939d0fe0b96759"},"ProductionBudget":"N/A","Movie":"Untitled Disney Live Action I (2020)","ReleaseDate":{"$date":"2020-02-14T00:00:00.000Z"},"Genre":"Unknown","Distributor":"Buena Vista","Runtime":"N/A","MPAARating":"Not Yet Rated"}
{"_id":{"$oid":"5c98d705e2939d0fe0b9675a"},"ProductionBudget":"N/A","Movie":"Untitled Kingsman Movie","ReleaseDate":{"$date":"2020-02-14T00:00:00.000Z"},"Genre":"Action Comedy","Distributor":"Fox","Runtime":"N/A","MPAARating":"Not Yet Rated"}
{"_id":{"$oid":"5c98d707e2939d0fe0b9675b"},"ProductionBudget":"N/A","Movie":"Untitled Will Packer Romance","ReleaseDate":{"$date":"2020-02-14T00:00:00.000Z"},"Genre":"Romance","Distributor":"Universal","Runtime":"N/A","MPAARating":"Not Yet Rated"}
{"_id":{"$oid":"5c98d709e2939d0fe0b9675c"},"ProductionBudget":"N/A","Movie":"Bloodshot","ReleaseDate":{"$date":"2020-02-21T00:00:00.000Z"},"Genre":"Action Fantasy","Distributor":"Sony / Columbia","Runtime":"N/A","MPAARating":"Unknown"}
{"_id":{"$oid":"5c98d70ae2939d0fe0b9675d"},"ProductionBudget":"N/A","Movie":"Blumhouse Fantasy Island Horror","ReleaseDate":{"$date":"2020-02-28T00:00:00.000Z"},"Genre":"Horror","Distributor":"Sony / Columbia","Runtime":"N/A","MPAARating":"Not Yet Rated"}
{"_id":{"$oid":"5c98d70ce2939d0fe0b9675e"},"ProductionBudget":"N/A","Movie":"The Lovebirds","ReleaseDate":{"$date":"2020-03-06T00:00:00.000Z"},"Genre":"Comedy","Distributor":"Paramount","Runtime":"N/A","MPAARating":"Unknown"}
{"_id":{"$oid":"5c98d70ee2939d0fe0b9675f"},"ProductionBudget":"N/A","Movie":"Onward","ReleaseDate":{"$date":"2020-03-06T00:00:00.000Z"},"Genre":"Animation","Distributor":"Buena Vista","Runtime":"N/A","MPAARating":"Not Yet Rated"}
{"_id":{"$oid":"5c98d70fe2939d0fe0b96760"},"ProductionBudget":"N/A","Movie":"Gambit","ReleaseDate":{"$date":"2020-03-13T00:00:00.000Z"},"Genre":"Action","Distributor":"Fox","Runtime":"N/A","MPAARating":"Not Yet Rated"}
{"_id":{"$oid":"5c98d711e2939d0fe0b96761"},"ProductionBudget":"N/A","Movie":"Godzilla vs. Kong","ReleaseDate":{"$date":"2020-03-13T00:00:00.000Z"},"Genre":"Action / Adventure","Distributor":"Warner Bros.","Runtime":"N/A","MPAARating":"Not Yet Rated"}
{"_id":{"$oid":"5c98d713e2939d0fe0b96762"},"ProductionBudget":"N/A","Movie":"Untitled Blumhouse Productions Project I (2020)","ReleaseDate":{"$date":"2020-03-13T00:00:00.000Z"},"Genre":"Unknown","Distributor":"Universal","Runtime":"N/A","MPAARating":"Not Yet Rated"}
{"_id":{"$oid":"5c98d715e2939d0fe0b96763"},"ProductionBudget":"N/A","Movie":"I Still Believe","ReleaseDate":{"$date":"2020-03-20T00:00:00.000Z"},"Genre":"Drama","Distributor":"Lionsgate","Runtime":"N/A","MPAARating":"Not Yet Rated"}
{"_id":{"$oid":"5c98d716e2939d0fe0b96764"},"ProductionBudget":"N/A","Movie":"Playing with Fire","ReleaseDate":{"$date":"2020-03-20T00:00:00.000Z"},"Genre":"Comedy","Distributor":"Paramount","Runtime":"N/A","MPAARating":"Unknown"}
{"_id":{"$oid":"5c98d717e2939d0fe0b96765"},"ProductionBudget":"N/A","Movie":"GI Joe","ReleaseDate":{"$date":"2020-03-27T00:00:00.000Z"},"Genre":"Action","Distributor":"Paramount","Runtime":"N/A","MPAARating":"Not Yet Rated"}
{"_id":{"$oid":"5c98d719e2939d0fe0b96766"},"ProductionBudget":"N/A","Movie":"Mulan (2020)","ReleaseDate":{"$date":"2020-03-27T00:00:00.000Z"},"Genre":"Fantasy","Distributor":"Buena Vista","Runtime":"N/A","MPAARating":"Not Yet Rated"}
{"_id":{"$oid":"5c98d71be2939d0fe0b96767"},"ProductionBudget":"N/A","Movie":"Untitled DC Film (April 2020)","ReleaseDate":{"$date":"2020-04-03T00:00:00.000Z"},"Genre":"Action / Adventure","Distributor":"Warner Bros.","Runtime":"N/A","MPAARating":"Not Yet Rated"}
{"_id":{"$oid":"5c98d71ce2939d0fe0b96768"},"ProductionBudget":"N/A","Movie":"James Bond 25","ReleaseDate":{"$date":"2020-04-08T00:00:00.000Z"},"Genre":"Action","Distributor":"MGM","Runtime":"N/A","MPAARating":"Not Yet Rated"}
{"_id":{"$oid":"5c98d71fe2939d0fe0b96769"},"ProductionBudget":"N/A","Movie":"Untitled Affirm Films Coach Project","ReleaseDate":{"$date":"2020-04-10T00:00:00.000Z"},"Genre":"Drama","Distributor":"Sony / AFFIRM Films","Runtime":"N/A","MPAARating":"Not Yet Rated"}
{"_id":{"$oid":"5c98d722e2939d0fe0b9676a"},"ProductionBudget":"N/A","Movie":"Escape Room 2","ReleaseDate":{"$date":"2020-04-17T00:00:00.000Z"},"Genre":"Horror","Distributor":"Sony / Columbia","Runtime":"N/A","MPAARating":"Not Yet Rated"}
{"_id":{"$oid":"5c98d726e2939d0fe0b9676b"},"ProductionBudget":"N/A","Movie":"Trolls World Tour","ReleaseDate":{"$date":"2020-04-17T00:00:00.000Z"},"Genre":"Animation","Distributor":"Universal","Runtime":"N/A","MPAARating":"Not Yet Rated"}
{"_id":{"$oid":"5c98d727e2939d0fe0b9676c"},"ProductionBudget":"N/A","Movie":"Untitled Marvel Movie (May 2020)","ReleaseDate":{"$date":"2020-05-01T00:00:00.000Z"},"Genre":"Action","Distributor":"Buena Vista","Runtime":"N/A","MPAARating":"Not Yet Rated"}
{"_id":{"$oid":"5c98d729e2939d0fe0b9676d"},"ProductionBudget":"N/A","Movie":"Greyhound","ReleaseDate":{"$date":"2020-05-08T00:00:00.000Z"},"Genre":"War Drama","Distributor":"Sony / Columbia","Runtime":"N/A","MPAARating":"Not Yet Rated"}
{"_id":{"$oid":"5c98d730e2939d0fe0b9676e"},"ProductionBudget":"N/A","Movie":"Legally Blonde 3","ReleaseDate":{"$date":"2020-05-08T00:00:00.000Z"},"Genre":"Comedy","Distributor":"MGM","Runtime":"N/A","MPAARating":"Not Yet Rated"}
{"_id":{"$oid":"5c98d732e2939d0fe0b9676f"},"ProductionBudget":"N/A","Movie":"Scooby","ReleaseDate":{"$date":"2020-05-15T00:00:00.000Z"},"Genre":"Animation","Distributor":"Warner Bros.","Runtime":"N/A","MPAARating":"Not Yet Rated"}
{"_id":{"$oid":"5c98d734e2939d0fe0b96770"},"ProductionBudget":"N/A","Movie":"Untitled 'A Quiet Place' Sequel","ReleaseDate":{"$date":"2020-05-15T00:00:00.000Z"},"Genre":"Horror","Distributor":"Paramount","Runtime":"N/A","MPAARating":"Not Yet Rated"}
{"_id":{"$oid":"5c98d735e2939d0fe0b96771"},"ProductionBudget":"N/A","Movie":"Will Packer Comedy I (2020)","ReleaseDate":{"$date":"2020-05-15T00:00:00.000Z"},"Genre":"Comedy","Distributor":"Universal","Runtime":"N/A","MPAARating":"Not Yet Rated"}
{"_id":{"$oid":"5c98d73de2939d0fe0b96772"},"ProductionBudget":"N/A","Movie":"Candyman (2020)","ReleaseDate":{"$date":"2020-06-12T00:00:00.000Z"},"Genre":"Horror","Distributor":"Universal","Runtime":"N/A","MPAARating":"Not Yet Rated"}
{"_id":{"$oid":"5c98d73ee2939d0fe0b96773"},"ProductionBudget":"N/A","Movie":"Untitled Judd Apatow/Pete Davidson Comedy","ReleaseDate":{"$date":"2020-06-19T00:00:00.000Z"},"Genre":"Comedy","Distributor":"Universal","Runtime":"N/A","MPAARating":"Unrated"}
{"_id":{"$oid":"5c98d740e2939d0fe0b96774"},"ProductionBudget":"N/A","Movie":"Untitled Pixar Animation (June 2020)","ReleaseDate":{"$date":"2020-06-19T00:00:00.000Z"},"Genre":"Animation","Distributor":"Buena Vista","Runtime":"N/A","MPAARating":"Not Yet Rated"}
{"_id":{"$oid":"5c98d742e2939d0fe0b96775"},"ProductionBudget":"N/A","Movie":"In the Heights","ReleaseDate":{"$date":"2020-06-26T00:00:00.000Z"},"Genre":"Music Drama","Distributor":"Warner Bros.","Runtime":"N/A","MPAARating":"Not Yet Rated"}
{"_id":{"$oid":"5c98d743e2939d0fe0b96776"},"ProductionBudget":"N/A","Movie":"Top Gun (2020)","ReleaseDate":{"$date":"2020-06-26T00:00:00.000Z"},"Genre":"Action","Distributor":"Paramount","Runtime":"N/A","MPAARating":"Not Yet Rated"}
{"_id":{"$oid":"5c98d745e2939d0fe0b96777"},"ProductionBudget":"N/A","Movie":"Untitled Fox/Marvel Film II (2020)","ReleaseDate":{"$date":"2020-06-26T00:00:00.000Z"},"Genre":"Action / Adventure","Distributor":"Fox","Runtime":"N/A","MPAARating":"Not Yet Rated"}
{"_id":{"$oid":"5c98d74ae2939d0fe0b96778"},"ProductionBudget":"N/A","Movie":"Free Guy","ReleaseDate":{"$date":"2020-07-03T00:00:00.000Z"},"Genre":"Action Comedy","Distributor":"Fox","Runtime":"N/A","MPAARating":"Not Yet Rated"}
{"_id":{"$oid":"5c98d74be2939d0fe0b96779"},"ProductionBudget":"N/A","Movie":"Minions 2","ReleaseDate":{"$date":"2020-07-03T00:00:00.000Z"},"Genre":"Animation","Distributor":"Universal","Runtime":"N/A","MPAARating":"Not Yet Rated"}
{"_id":{"$oid":"5c98d74de2939d0fe0b9677a"},"ProductionBudget":"N/A","Movie":"Untitled Ghostbusters","ReleaseDate":{"$date":"2020-07-10T00:00:00.000Z"},"Genre":"Action Comedy","Distributor":"Sony / Columbia","Runtime":"N/A","MPAARating":"Not Yet Rated"}
{"_id":{"$oid":"5c98d74fe2939d0fe0b9677b"},"ProductionBudget":"N/A","Movie":"Bob's Burgers","ReleaseDate":{"$date":"2020-07-17T00:00:00.000Z"},"Genre":"Animation","Distributor":"Fox","Runtime":"N/A","MPAARating":"Unrated"}
{"_id":{"$oid":"5c98d751e2939d0fe0b9677c"},"ProductionBudget":"N/A","Movie":"Untitled Christopher Nolan Event Film","ReleaseDate":{"$date":"2020-07-17T00:00:00.000Z"},"Genre":"Unknown","Distributor":"Warner Bros.","Runtime":"N/A","MPAARating":"Not Yet Rated"}
{"_id":{"$oid":"5c98d753e2939d0fe0b9677d"},"ProductionBudget":"N/A","Movie":"Untitled Paramount Animation","ReleaseDate":{"$date":"2020-07-17T00:00:00.000Z"},"Genre":"Animation","Distributor":"Paramount","Runtime":"N/A","MPAARating":"Not Yet Rated"}
{"_id":{"$oid":"5c98d754e2939d0fe0b9677e"},"ProductionBudget":"N/A","Movie":"Untitled Universal Event Film II (2020)","ReleaseDate":{"$date":"2020-07-17T00:00:00.000Z"},"Genre":"Unknown","Distributor":"Universal","Runtime":"N/A","MPAARating":"Not Yet Rated"}
{"_id":{"$oid":"5c98d759e2939d0fe0b9677f"},"ProductionBudget":"N/A","Movie":"Jungle Cruise","ReleaseDate":{"$date":"2020-07-24T00:00:00.000Z"},"Genre":"Adventure","Distributor":"Buena Vista","Runtime":"N/A","MPAARating":"Not Yet Rated"}
{"_id":{"$oid":"5c98d75be2939d0fe0b96780"},"ProductionBudget":"N/A","Movie":"Sony/Marvel Morbius","ReleaseDate":{"$date":"2020-07-31T00:00:00.000Z"},"Genre":"Action Horror","Distributor":"Columbia","Runtime":"N/A","MPAARating":"Not Yet Rated"}
{"_id":{"$oid":"5c98d75ce2939d0fe0b96781"},"ProductionBudget":"N/A","Movie":"Untitled Coming to America Sequel","ReleaseDate":{"$date":"2020-08-07T00:00:00.000Z"},"Genre":"Comedy","Distributor":"Paramount","Runtime":"N/A","MPAARating":"Not Yet Rated"}
{"_id":{"$oid":"5c98d765e2939d0fe0b96782"},"ProductionBudget":"N/A","Movie":"Untitled WB Event Film #1 (2020)","ReleaseDate":{"$date":"2020-08-07T00:00:00.000Z"},"Genre":"Unknown","Distributor":"Warner Bros.","Runtime":"N/A","MPAARating":"Not Yet Rated"}
{"_id":{"$oid":"5c98d766e2939d0fe0b96783"},"ProductionBudget":"N/A","Movie":"Untitled Universal Event Film III (2020)","ReleaseDate":{"$date":"2020-08-14T00:00:00.000Z"},"Genre":"Unknown","Distributor":"Universal","Runtime":"N/A","MPAARating":"Not Yet Rated"}
{"_id":{"$oid":"5c98d768e2939d0fe0b96784"},"ProductionBudget":"N/A","Movie":"Monster Hunter","ReleaseDate":{"$date":"2020-09-04T00:00:00.000Z"},"Genre":"Action Fantasy","Distributor":"Sony / Screen Gems","Runtime":"N/A","MPAARating":"Not Yet Rated"}
{"_id":{"$oid":"5c98d769e2939d0fe0b96785"},"ProductionBudget":"N/A","Movie":"Untitled Conjuring Universe Film (2020)","ReleaseDate":{"$date":"2020-09-11T00:00:00.000Z"},"Genre":"Horror","Distributor":"Warner Bros. (New Line)","Runtime":"N/A","MPAARating":"Not Yet Rated"}
{"_id":{"$oid":"5c98d76ae2939d0fe0b96786"},"ProductionBudget":"N/A","Movie":"The Croods 2","ReleaseDate":{"$date":"2020-09-18T00:00:00.000Z"},"Genre":"Animation","Distributor":"Universal","Runtime":"N/A","MPAARating":"Not Yet Rated"}
{"_id":{"$oid":"5c98d76ce2939d0fe0b96787"},"ProductionBudget":"N/A","Movie":"Tom Clancy's Without Remorse","ReleaseDate":{"$date":"2020-09-18T00:00:00.000Z"},"Genre":"Action","Distributor":"Paramount","Runtime":"N/A","MPAARating":"Not Yet Rated"}
{"_id":{"$oid":"5c98d76de2939d0fe0b96788"},"ProductionBudget":"N/A","Movie":"The Many Saints of Newark","ReleaseDate":{"$date":"2020-09-25T00:00:00.000Z"},"Genre":"Crime Drama","Distributor":"Warner Bros.","Runtime":"N/A","MPAARating":"Not Yet Rated"}
{"_id":{"$oid":"5c98d76fe2939d0fe0b96789"},"ProductionBudget":"N/A","Movie":"SPA Animated Franchise II (2020)","ReleaseDate":{"$date":"2020-09-25T00:00:00.000Z"},"Genre":"Animation","Distributor":"Sony / Columbia","Runtime":"N/A","MPAARating":"Not Yet Rated"}
{"_id":{"$oid":"5c98d773e2939d0fe0b9678a"},"ProductionBudget":"N/A","Movie":"Bios","ReleaseDate":{"$date":"2020-10-02T00:00:00.000Z"},"Genre":"Sci-Fi","Distributor":"Universal","Runtime":"N/A","MPAARating":"Not Yet Rated"}
{"_id":{"$oid":"5c98d77be2939d0fe0b9678b"},"ProductionBudget":"N/A","Movie":"Death on the Nile (2019)","ReleaseDate":{"$date":"2020-10-02T00:00:00.000Z"},"Genre":"Thriller","Distributor":"Fox","Runtime":"N/A","MPAARating":"Not Yet Rated"}
{"_id":{"$oid":"5c98d77de2939d0fe0b9678c"},"ProductionBudget":"N/A","Movie":"Untitled Fox/Marvel Film III (2020)","ReleaseDate":{"$date":"2020-10-02T00:00:00.000Z"},"Genre":"Action / Adventure","Distributor":"Fox","Runtime":"N/A","MPAARating":"Not Yet Rated"}
{"_id":{"$oid":"5c98d77fe2939d0fe0b9678d"},"ProductionBudget":"N/A","Movie":"Untitled Sony/Marvel Sequel (2020)","ReleaseDate":{"$date":"2020-10-02T00:00:00.000Z"},"Genre":"Action","Distributor":"Columbia","Runtime":"N/A","MPAARating":"Not Yet Rated"}
{"_id":{"$oid":"5c98d782e2939d0fe0b9678e"},"ProductionBudget":"N/A","Movie":"Untitled Disney Live Action IV (2020)","ReleaseDate":{"$date":"2020-10-09T00:00:00.000Z"},"Genre":"Unknown","Distributor":"Buena Vista","Runtime":"N/A","MPAARating":"Not Yet Rated"}
{"_id":{"$oid":"5c98d783e2939d0fe0b9678f"},"ProductionBudget":"N/A","Movie":"Micronauts","ReleaseDate":{"$date":"2020-10-16T00:00:00.000Z"},"Genre":"Action","Distributor":"Paramount","Runtime":"N/A","MPAARating":"Not Yet Rated"}
{"_id":{"$oid":"5c98d784e2939d0fe0b96790"},"ProductionBudget":"N/A","Movie":"Untitled Blumhouse Productions Project II (2020)","ReleaseDate":{"$date":"2020-10-16T00:00:00.000Z"},"Genre":"Unknown","Distributor":"Universal","Runtime":"N/A","MPAARating":"Not Yet Rated"}
{"_id":{"$oid":"5c98d786e2939d0fe0b96791"},"ProductionBudget":"N/A","Movie":"The Witches (2020)","ReleaseDate":{"$date":"2020-10-16T00:00:00.000Z"},"Genre":"Horror","Distributor":"Warner Bros.","Runtime":"N/A","MPAARating":"Not Yet Rated"}
{"_id":{"$oid":"5c98d787e2939d0fe0b96792"},"ProductionBudget":"N/A","Movie":"Untitled Universal Event Comedy","ReleaseDate":{"$date":"2020-10-23T00:00:00.000Z"},"Genre":"Comedy","Distributor":"Universal","Runtime":"N/A","MPAARating":"Not Yet Rated"}
{"_id":{"$oid":"5c98d78ce2939d0fe0b96793"},"ProductionBudget":"N/A","Movie":"Untitled Marvel Movie (November 2020)","ReleaseDate":{"$date":"2020-11-06T00:00:00.000Z"},"Genre":"Action","Distributor":"Buena Vista","Runtime":"N/A","MPAARating":"Not Yet Rated"}
{"_id":{"$oid":"5c98d78de2939d0fe0b96794"},"ProductionBudget":"N/A","Movie":"Vivo","ReleaseDate":{"$date":"2020-11-06T00:00:00.000Z"},"Genre":"Animation","Distributor":"Sony / Columbia","Runtime":"N/A","MPAARating":"Not Yet Rated"}
{"_id":{"$oid":"5c98d78fe2939d0fe0b96795"},"ProductionBudget":"N/A","Movie":"Red Notice","ReleaseDate":{"$date":"2020-11-13T00:00:00.000Z"},"Genre":"Action Thriller","Distributor":"Universal","Runtime":"N/A","MPAARating":"Not Yet Rated"}
{"_id":{"$oid":"5c98d792e2939d0fe0b96796"},"ProductionBudget":"N/A","Movie":"Untitled Family Event Movie","ReleaseDate":{"$date":"2020-11-13T00:00:00.000Z"},"Genre":"Family Adventure","Distributor":"Paramount","Runtime":"N/A","MPAARating":"Not Yet Rated"}
{"_id":{"$oid":"5c98d793e2939d0fe0b96797"},"ProductionBudget":"N/A","Movie":"Untitled Universal Event Film IV (2020)","ReleaseDate":{"$date":"2020-11-13T00:00:00.000Z"},"Genre":"Unknown","Distributor":"Universal","Runtime":"N/A","MPAARating":"Not Yet Rated"}
{"_id":{"$oid":"5c98d794e2939d0fe0b96798"},"ProductionBudget":"N/A","Movie":"Dune","ReleaseDate":{"$date":"2020-11-20T00:00:00.000Z"},"Genre":"Action / Adventure","Distributor":"Warner Bros.","Runtime":"N/A","MPAARating":"Not Yet Rated"}
{"_id":{"$oid":"5c98d796e2939d0fe0b96799"},"ProductionBudget":"N/A","Movie":"Untitled Disney Animation (3D)","ReleaseDate":{"$date":"2020-11-25T00:00:00.000Z"},"Genre":"Animation","Distributor":"Buena Vista","Runtime":"N/A","MPAARating":"Not Yet Rated"}
{"_id":{"$oid":"5c98d797e2939d0fe0b9679a"},"ProductionBudget":"N/A","Movie":"Avatar 2","ReleaseDate":{"$date":"2020-12-18T00:00:00.000Z"},"Genre":"Sci-Fi Adventure","Distributor":"Fox","Runtime":"N/A","MPAARating":"Not Yet Rated"}
{"_id":{"$oid":"5c98d799e2939d0fe0b9679b"},"ProductionBudget":"N/A","Movie":"Untitled Disney Live Action V (2020)","ReleaseDate":{"$date":"2020-12-23T00:00:00.000Z"},"Genre":"Unknown","Distributor":"Buena Vista","Runtime":"N/A","MPAARating":"Not Yet Rated"}
{"_id":{"$oid":"5c98d79ce2939d0fe0b9679c"},"ProductionBudget":"N/A","Movie":"Sing 2","ReleaseDate":{"$date":"2020-12-25T00:00:00.000Z"},"Genre":"Animation","Distributor":"Universal","Runtime":"N/A","MPAARating":"Not Yet Rated"}
{"_id":{"$oid":"5c98d79ee2939d0fe0b9679d"},"ProductionBudget":"N/A","Movie":"Untitled Paramount/Skydance Event Movie","ReleaseDate":{"$date":"2020-12-25T00:00:00.000Z"},"Genre":"Unknown","Distributor":"Paramount","Runtime":"N/A","MPAARating":"Not Yet Rated"}
{"_id":{"$oid":"5c98d79fe2939d0fe0b9679e"},"ProductionBudget":"N/A","Movie":"Untitled WB Event Film #2 (2020)","ReleaseDate":{"$date":"2020-12-25T00:00:00.000Z"},"Genre":"Unknown","Distributor":"Warner Bros.","Runtime":"N/A","MPAARating":"Not Yet Rated"}
{"_id":{"$oid":"5c98d7a1e2939d0fe0b9679f"},"ProductionBudget":"N/A","Movie":"Untitled Blumhouse Productions Project I (2021)","ReleaseDate":{"$date":"2021-01-08T00:00:00.000Z"},"Genre":"Unknown","Distributor":"Universal","Runtime":"N/A","MPAARating":"Not Yet Rated"}
{"_id":{"$oid":"5c98d7a3e2939d0fe0b967a0"},"ProductionBudget":"N/A","Movie":"Untitled Sesame Street Film","ReleaseDate":{"$date":"2021-01-15T00:00:00.000Z"},"Genre":"Musical","Distributor":"Warner Bros.","Runtime":"N/A","MPAARating":"Not Yet Rated"}
{"_id":{"$oid":"5c98d7a4e2939d0fe0b967a1"},"ProductionBudget":"N/A","Movie":"Rugrats","ReleaseDate":{"$date":"2021-01-29T00:00:00.000Z"},"Genre":"Animation","Distributor":"Paramount","Runtime":"N/A","MPAARating":"Not Yet Rated"}
{"_id":{"$oid":"5c98d7a7e2939d0fe0b967a2"},"ProductionBudget":"N/A","Movie":"Untitled Marvel II (2021)","ReleaseDate":{"$date":"2021-02-12T00:00:00.000Z"},"Genre":"Unknown","Distributor":"Buena Vista","Runtime":"N/A","MPAARating":"Not Yet Rated"}
{"_id":{"$oid":"5c98d7a9e2939d0fe0b967a3"},"ProductionBudget":"N/A","Movie":"Untitled Paramount Animation (2021)","ReleaseDate":{"$date":"2021-02-12T00:00:00.000Z"},"Genre":"Animation","Distributor":"Paramount","Runtime":"N/A","MPAARating":"Not Yet Rated"}
{"_id":{"$oid":"5c98d7aae2939d0fe0b967a4"},"ProductionBudget":"N/A","Movie":"Untitled WB Event Film #2 (2021)","ReleaseDate":{"$date":"2021-02-12T00:00:00.000Z"},"Genre":"Unknown","Distributor":"Warner Bros.","Runtime":"N/A","MPAARating":"Not Yet Rated"}
{"_id":{"$oid":"5c98d7ace2939d0fe0b967a5"},"ProductionBudget":"N/A","Movie":"Foster","ReleaseDate":{"$date":"2021-03-05T00:00:00.000Z"},"Genre":"Animation","Distributor":"Fox","Runtime":"N/A","MPAARating":"Not Yet Rated"}
{"_id":{"$oid":"5c98d7aee2939d0fe0b967a6"},"ProductionBudget":"N/A","Movie":"Untitled Fox/Marvel Film (2021)","ReleaseDate":{"$date":"2021-03-05T00:00:00.000Z"},"Genre":"Action / Adventure","Distributor":"Fox","Runtime":"N/A","MPAARating":"Not Yet Rated"}
{"_id":{"$oid":"5c98d7afe2939d0fe0b967a7"},"ProductionBudget":"N/A","Movie":"Untitled Disney Live Action (2021)","ReleaseDate":{"$date":"2021-03-12T00:00:00.000Z"},"Genre":"Unknown","Distributor":"Buena Vista","Runtime":"N/A","MPAARating":"Not Yet Rated"}
{"_id":{"$oid":"5c98d7b1e2939d0fe0b967a8"},"ProductionBudget":"N/A","Movie":"The Boss Baby 2","ReleaseDate":{"$date":"2021-03-26T00:00:00.000Z"},"Genre":"Animation","Distributor":"Universal","Runtime":"N/A","MPAARating":"Not Yet Rated"}
{"_id":{"$oid":"5c98d7b6e2939d0fe0b967a9"},"ProductionBudget":"N/A","Movie":"Untitled Tom \u0026 Jerry Film","ReleaseDate":{"$date":"2021-04-16T00:00:00.000Z"},"Genre":"Family Comedy","Distributor":"Warner Bros.","Runtime":"N/A","MPAARating":"Not Yet Rated"}
{"_id":{"$oid":"5c98d7b7e2939d0fe0b967aa"},"ProductionBudget":"N/A","Movie":"Untitled Marvel I (2021)","ReleaseDate":{"$date":"2021-05-07T00:00:00.000Z"},"Genre":"Unknown","Distributor":"Buena Vista","Runtime":"N/A","MPAARating":"Not Yet Rated"}
{"_id":{"$oid":"5c98d7bae2939d0fe0b967ab"},"ProductionBudget":"N/A","Movie":"DC Super Pets","ReleaseDate":{"$date":"2021-05-21T00:00:00.000Z"},"Genre":"Animation","Distributor":"Warner Bros.","Runtime":"N/A","MPAARating":"Not Yet Rated"}
{"_id":{"$oid":"5c98d7bce2939d0fe0b967ac"},"ProductionBudget":"N/A","Movie":"Untitled Disney Live Action II (2021)","ReleaseDate":{"$date":"2021-05-28T00:00:00.000Z"},"Genre":"Unknown","Distributor":"Buena Vista","Runtime":"N/A","MPAARating":"Not Yet Rated"}
{"_id":{"$oid":"5c98d7bee2939d0fe0b967ad"},"ProductionBudget":"N/A","Movie":"Jurassic World 3","ReleaseDate":{"$date":"2021-06-11T00:00:00.000Z"},"Genre":"Action / Adventure","Distributor":"Universal","Runtime":"N/A","MPAARating":"Not Yet Rated"}
{"_id":{"$oid":"5c98d7c2e2939d0fe0b967ae"},"ProductionBudget":"N/A","Movie":"Untitled Pixar Animation (3D)","ReleaseDate":{"$date":"2021-06-18T00:00:00.000Z"},"Genre":"Animation","Distributor":"Buena Vista","Runtime":"N/A","MPAARating":"Not Yet Rated"}
{"_id":{"$oid":"5c98d7c3e2939d0fe0b967af"},"ProductionBudget":"N/A","Movie":"The Batman","ReleaseDate":{"$date":"2021-06-25T00:00:00.000Z"},"Genre":"Action / Adventure","Distributor":"Warner Bros.","Runtime":"N/A","MPAARating":"Not Yet Rated"}
{"_id":{"$oid":"5c98d7c5e2939d0fe0b967b0"},"ProductionBudget":"N/A","Movie":"Untitled Illumination Animated Film (2021)","ReleaseDate":{"$date":"2021-07-02T00:00:00.000Z"},"Genre":"Animation","Distributor":"Universal","Runtime":"N/A","MPAARating":"Not Yet Rated"}
{"_id":{"$oid":"5c98d7c7e2939d0fe0b967b1"},"ProductionBudget":"N/A","Movie":"Untitled Indiana Jones (2019)","ReleaseDate":{"$date":"2021-07-09T00:00:00.000Z"},"Genre":"Adventure","Distributor":"Buena Vista","Runtime":"N/A","MPAARating":"Unknown"}
{"_id":{"$oid":"5c98d7c8e2939d0fe0b967b2"},"ProductionBudget":"N/A","Movie":"Space Jam 2","ReleaseDate":{"$date":"2021-07-16T00:00:00.000Z"},"Genre":"Action Comedy","Distributor":"Warner Bros.","Runtime":"N/A","MPAARating":"Not Yet Rated"}
{"_id":{"$oid":"5c98d7cae2939d0fe0b967b3"},"ProductionBudget":"N/A","Movie":"Mission: Impossible 7","ReleaseDate":{"$date":"2021-07-23T00:00:00.000Z"},"Genre":"Action","Distributor":"Paramount","Runtime":"N/A","MPAARating":"Not Yet Rated"}
{"_id":{"$oid":"5c98d7cbe2939d0fe0b967b4"},"ProductionBudget":"N/A","Movie":"Untitled Disney Live Action III (2021)","ReleaseDate":{"$date":"2021-07-30T00:00:00.000Z"},"Genre":"Unknown","Distributor":"Buena Vista","Runtime":"N/A","MPAARating":"Not Yet Rated"}
{"_id":{"$oid":"5c98d7cde2939d0fe0b967b5"},"ProductionBudget":"N/A","Movie":"The Suicide Squad","ReleaseDate":{"$date":"2021-08-06T00:00:00.000Z"},"Genre":"Action / Adventure","Distributor":"Warner Bros.","Runtime":"N/A","MPAARating":"Not Yet Rated"}
{"_id":{"$oid":"5c98d7cfe2939d0fe0b967b6"},"ProductionBudget":"N/A","Movie":"Untitled Blumhouse Productions Project II (2021)","ReleaseDate":{"$date":"2021-08-13T00:00:00.000Z"},"Genre":"Unknown","Distributor":"Universal","Runtime":"N/A","MPAARating":"Not Yet Rated"}
{"_id":{"$oid":"5c98d7d1e2939d0fe0b967b7"},"ProductionBudget":"N/A","Movie":"Untitled New Line Horror Film (2021)","ReleaseDate":{"$date":"2021-09-10T00:00:00.000Z"},"Genre":"Horror","Distributor":"Warner Bros. (New Line)","Runtime":"N/A","MPAARating":"Not Yet Rated"}
{"_id":{"$oid":"5c98d7d3e2939d0fe0b967b8"},"ProductionBudget":"N/A","Movie":"Spooky Jack","ReleaseDate":{"$date":"2021-09-17T00:00:00.000Z"},"Genre":"Animation","Distributor":"Universal","Runtime":"N/A","MPAARating":"Not Yet Rated"}
{"_id":{"$oid":"5c98d7d5e2939d0fe0b967b9"},"ProductionBudget":"N/A","Movie":"Untitled Paramount/Hasbro Event Film","ReleaseDate":{"$date":"2021-10-01T00:00:00.000Z"},"Genre":"Unknown","Distributor":"Paramount","Runtime":"N/A","MPAARating":"Not Yet Rated"}
{"_id":{"$oid":"5c98d7d7e2939d0fe0b967ba"},"ProductionBudget":"N/A","Movie":"Untitled WB Event Film I (2021)","ReleaseDate":{"$date":"2021-10-01T00:00:00.000Z"},"Genre":"Unknown","Distributor":"Warner Bros.","Runtime":"N/A","MPAARating":"Not Yet Rated"}
{"_id":{"$oid":"5c98d7d8e2939d0fe0b967bb"},"ProductionBudget":"N/A","Movie":"Untitled Disney Live Action IV (2021)","ReleaseDate":{"$date":"2021-10-08T00:00:00.000Z"},"Genre":"Unknown","Distributor":"Buena Vista","Runtime":"N/A","MPAARating":"Not Yet Rated"}
{"_id":{"$oid":"5c98d7dae2939d0fe0b967bc"},"ProductionBudget":"N/A","Movie":"Untitled Blumhouse Productions Project III (2021)","ReleaseDate":{"$date":"2021-10-15T00:00:00.000Z"},"Genre":"Unknown","Distributor":"Universal","Runtime":"N/A","MPAARating":"Not Yet Rated"}
{"_id":{"$oid":"5c98d7dce2939d0fe0b967bd"},"ProductionBudget":"N/A","Movie":"Untitled Marvel III (2021)","ReleaseDate":{"$date":"2021-11-05T00:00:00.000Z"},"Genre":"Unknown","Distributor":"Buena Vista","Runtime":"N/A","MPAARating":"Not Yet Rated"}
{"_id":{"$oid":"5c98d7dde2939d0fe0b967be"},"ProductionBudget":"N/A","Movie":"Untitled WB Event Film II (2021)","ReleaseDate":{"$date":"2021-11-12T00:00:00.000Z"},"Genre":"Unknown","Distributor":"Warner Bros.","Runtime":"N/A","MPAARating":"Not Yet Rated"}
{"_id":{"$oid":"5c98d7dfe2939d0fe0b967bf"},"ProductionBudget":"N/A","Movie":"Dungeons \u0026 Dragons (2021)","ReleaseDate":{"$date":"2021-11-19T00:00:00.000Z"},"Genre":"Fantasy","Distributor":"Paramount","Runtime":"N/A","MPAARating":"Not Yet Rated"}
{"_id":{"$oid":"5c98d7e0e2939d0fe0b967c0"},"ProductionBudget":"N/A","Movie":"Untitled Disney Animation (Nov 2021)","ReleaseDate":{"$date":"2021-11-24T00:00:00.000Z"},"Genre":"Animation","Distributor":"Buena Vista","Runtime":"N/A","MPAARating":"Unknown"}
{"_id":{"$oid":"5c98d7e2e2939d0fe0b967c1"},"ProductionBudget":"N/A","Movie":"Avatar 3","ReleaseDate":{"$date":"2021-12-17T00:00:00.000Z"},"Genre":"Sci-Fi Adventure","Distributor":"Fox","Runtime":"N/A","MPAARating":"Not Yet Rated"}
{"_id":{"$oid":"5c98d7e3e2939d0fe0b967c2"},"ProductionBudget":"N/A","Movie":"Hotel Transylvania 4","ReleaseDate":{"$date":"2021-12-22T00:00:00.000Z"},"Genre":"Animation","Distributor":"Sony / Columbia","Runtime":"N/A","MPAARating":"Not Yet Rated"}
{"_id":{"$oid":"5c98d7e7e2939d0fe0b967c3"},"ProductionBudget":"N/A","Movie":"Sherlock Holmes 3","ReleaseDate":{"$date":"2021-12-22T00:00:00.000Z"},"Genre":"Adventure","Distributor":"Warner Bros.","Runtime":"N/A","MPAARating":"Not Yet Rated"}
{"_id":{"$oid":"5c98d7e8e2939d0fe0b967c4"},"ProductionBudget":"N/A","Movie":"Untitled Disney Live Action V (2021)","ReleaseDate":{"$date":"2021-12-22T00:00:00.000Z"},"Genre":"Unknown","Distributor":"Buena Vista","Runtime":"N/A","MPAARating":"Not Yet Rated"}
{"_id":{"$oid":"5c98d7eae2939d0fe0b967c5"},"ProductionBudget":"N/A","Movie":"Wicked","ReleaseDate":{"$date":"2021-12-22T00:00:00.000Z"},"Genre":"Musical","Distributor":"Universal","Runtime":"N/A","MPAARating":"Not Yet Rated"}
